{
"meta":{"test_sets":[],"test_metrics":[],"learn_metrics":[{"best_value":"Min","name":"RMSE"}],"launch_mode":"Train","parameters":"","iteration_count":1000,"learn_sets":["learn"],"name":"experiment"},
"iterations":[
{"learn":[178.7665845],"iteration":0,"passed_time":0.0005165279444,"remaining_time":0.5160114165},
{"learn":[172.6516152],"iteration":1,"passed_time":0.001095685939,"remaining_time":0.5467472838},
{"learn":[166.6671603],"iteration":2,"passed_time":0.001650707769,"remaining_time":0.5485852152},
{"learn":[160.7083523],"iteration":3,"passed_time":0.002039236047,"remaining_time":0.5077697758},
{"learn":[155.2695261],"iteration":4,"passed_time":0.002588358814,"remaining_time":0.5150834039},
{"learn":[149.8638858],"iteration":5,"passed_time":0.003143010702,"remaining_time":0.5206921063},
{"learn":[144.4588086],"iteration":6,"passed_time":0.003713850018,"remaining_time":0.5268361526},
{"learn":[139.4259286],"iteration":7,"passed_time":0.004264182593,"remaining_time":0.5287586415},
{"learn":[134.589287],"iteration":8,"passed_time":0.00483344216,"remaining_time":0.5322156867},
{"learn":[129.8945151],"iteration":9,"passed_time":0.005377085797,"remaining_time":0.5323314939},
{"learn":[125.3339766],"iteration":10,"passed_time":0.005943555808,"remaining_time":0.5343796994},
{"learn":[120.8209068],"iteration":11,"passed_time":0.006489899016,"remaining_time":0.5343350189},
{"learn":[116.5319646],"iteration":12,"passed_time":0.007034102563,"remaining_time":0.53405071},
{"learn":[112.5670358],"iteration":13,"passed_time":0.007572866975,"remaining_time":0.5333462027},
{"learn":[108.7152488],"iteration":14,"passed_time":0.008135867537,"remaining_time":0.5342553016},
{"learn":[104.9070903],"iteration":15,"passed_time":0.008694558784,"remaining_time":0.5347153652},
{"learn":[101.3058349],"iteration":16,"passed_time":0.009257509353,"remaining_time":0.5353018644},
{"learn":[97.83617812],"iteration":17,"passed_time":0.009851405007,"remaining_time":0.5374488732},
{"learn":[94.37766039],"iteration":18,"passed_time":0.01042949317,"remaining_time":0.5384912001},
{"learn":[91.09379626],"iteration":19,"passed_time":0.01099616315,"remaining_time":0.5388119944},
{"learn":[87.86421501],"iteration":20,"passed_time":0.01155393454,"remaining_time":0.5386334247},
{"learn":[84.83187423],"iteration":21,"passed_time":0.01210606683,"remaining_time":0.5381696983},
{"learn":[81.89468059],"iteration":22,"passed_time":0.01268093551,"remaining_time":0.5386640866},
{"learn":[79.06684544],"iteration":23,"passed_time":0.01325222475,"remaining_time":0.5389238066},
{"learn":[76.35683375],"iteration":24,"passed_time":0.01381110597,"remaining_time":0.5386331328},
{"learn":[73.74048859],"iteration":25,"passed_time":0.0143717669,"remaining_time":0.5383884986},
{"learn":[71.29188289],"iteration":26,"passed_time":0.0149206897,"remaining_time":0.5376974474},
{"learn":[68.80358526],"iteration":27,"passed_time":0.01548395022,"remaining_time":0.537514272},
{"learn":[66.55278359],"iteration":28,"passed_time":0.0160474807,"remaining_time":0.5373139227},
{"learn":[64.23716894],"iteration":29,"passed_time":0.01663321765,"remaining_time":0.5378073707},
{"learn":[62.01883238],"iteration":30,"passed_time":0.01718643976,"remaining_time":0.537214843},
{"learn":[59.94867162],"iteration":31,"passed_time":0.01777702594,"remaining_time":0.5377550348},
{"learn":[57.94447906],"iteration":32,"passed_time":0.01833368751,"remaining_time":0.5372326008},
{"learn":[55.9667263],"iteration":33,"passed_time":0.01887588138,"remaining_time":0.5362971004},
{"learn":[54.01073998],"iteration":34,"passed_time":0.01941198621,"remaining_time":0.5352161913},
{"learn":[52.10991519],"iteration":35,"passed_time":0.01994505153,"remaining_time":0.5340841577},
{"learn":[50.36055722],"iteration":36,"passed_time":0.02031490278,"remaining_time":0.5287365236},
{"learn":[48.57023275],"iteration":37,"passed_time":0.02086118599,"remaining_time":0.5281173928},
{"learn":[46.87867237],"iteration":38,"passed_time":0.02140513958,"remaining_time":0.5274445933},
{"learn":[45.2716965],"iteration":39,"passed_time":0.0219589616,"remaining_time":0.5270150785},
{"learn":[43.81221543],"iteration":40,"passed_time":0.02251153382,"remaining_time":0.5265502667},
{"learn":[42.2567689],"iteration":41,"passed_time":0.02307177482,"remaining_time":0.5262561971},
{"learn":[40.83071799],"iteration":42,"passed_time":0.02364736338,"remaining_time":0.5262913199},
{"learn":[39.44025263],"iteration":43,"passed_time":0.0242012254,"remaining_time":0.5258266245},
{"learn":[38.05740552],"iteration":44,"passed_time":0.02473292093,"remaining_time":0.5248875442},
{"learn":[36.79824335],"iteration":45,"passed_time":0.02528747284,"remaining_time":0.5244401975},
{"learn":[35.67861407],"iteration":46,"passed_time":0.02582890682,"remaining_time":0.5237223022},
{"learn":[34.49096815],"iteration":47,"passed_time":0.02637140064,"remaining_time":0.5230327794},
{"learn":[33.29254323],"iteration":48,"passed_time":0.02694112014,"remaining_time":0.5228776582},
{"learn":[32.15234036],"iteration":49,"passed_time":0.02748577361,"remaining_time":0.5222296987},
{"learn":[31.11764652],"iteration":50,"passed_time":0.02803086702,"remaining_time":0.5215939765},
{"learn":[30.02636906],"iteration":51,"passed_time":0.02875485713,"remaining_time":0.5242231646},
{"learn":[29.02039056],"iteration":52,"passed_time":0.02941553754,"remaining_time":0.5255946047},
{"learn":[28.04410854],"iteration":53,"passed_time":0.0299861169,"remaining_time":0.5253123442},
{"learn":[27.09835607],"iteration":54,"passed_time":0.03061312729,"remaining_time":0.5259891871},
{"learn":[26.18979305],"iteration":55,"passed_time":0.03120572242,"remaining_time":0.5260393208},
{"learn":[25.33432865],"iteration":56,"passed_time":0.03183623762,"remaining_time":0.526694247},
{"learn":[24.48916078],"iteration":57,"passed_time":0.03245943838,"remaining_time":0.5271860509},
{"learn":[23.69497615],"iteration":58,"passed_time":0.03309384247,"remaining_time":0.5278187418},
{"learn":[22.93843189],"iteration":59,"passed_time":0.03374824388,"remaining_time":0.5287224875},
{"learn":[22.17594923],"iteration":60,"passed_time":0.0343055451,"remaining_time":0.5280804402},
{"learn":[21.46331025],"iteration":61,"passed_time":0.03495962144,"remaining_time":0.5289052405},
{"learn":[20.78947361],"iteration":62,"passed_time":0.0356000997,"remaining_time":0.5294808478},
{"learn":[20.11415081],"iteration":63,"passed_time":0.03622393059,"remaining_time":0.5297749849},
{"learn":[19.53111867],"iteration":64,"passed_time":0.03686668848,"remaining_time":0.5303131344},
{"learn":[18.9125804],"iteration":65,"passed_time":0.03749689813,"remaining_time":0.530637922},
{"learn":[18.29212379],"iteration":66,"passed_time":0.03813571664,"remaining_time":0.531054084},
{"learn":[17.71043457],"iteration":67,"passed_time":0.03873510143,"remaining_time":0.5308987431},
{"learn":[17.16419905],"iteration":68,"passed_time":0.03934687424,"remaining_time":0.53089768},
{"learn":[16.61183415],"iteration":69,"passed_time":0.03997344031,"remaining_time":0.531075707},
{"learn":[16.10375215],"iteration":70,"passed_time":0.04059741582,"remaining_time":0.5311971732},
{"learn":[15.58388839],"iteration":71,"passed_time":0.04122760547,"remaining_time":0.531378026},
{"learn":[15.10620427],"iteration":72,"passed_time":0.04185348628,"remaining_time":0.5314819423},
{"learn":[14.63633573],"iteration":73,"passed_time":0.04249814851,"remaining_time":0.5318011556},
{"learn":[14.17832436],"iteration":74,"passed_time":0.04316139851,"remaining_time":0.5323239149},
{"learn":[13.71670874],"iteration":75,"passed_time":0.0437962974,"remaining_time":0.5324707737},
{"learn":[13.29711241],"iteration":76,"passed_time":0.0444405953,"remaining_time":0.532709993},
{"learn":[12.88269693],"iteration":77,"passed_time":0.04504759423,"remaining_time":0.5324856652},
{"learn":[12.4959009],"iteration":78,"passed_time":0.04566138136,"remaining_time":0.5323307878},
{"learn":[12.16032387],"iteration":79,"passed_time":0.04626674495,"remaining_time":0.5320675669},
{"learn":[11.80157848],"iteration":80,"passed_time":0.046916322,"remaining_time":0.5322975299},
{"learn":[11.45593066],"iteration":81,"passed_time":0.04757341225,"remaining_time":0.5325901518},
{"learn":[11.13093511],"iteration":82,"passed_time":0.04820504727,"remaining_time":0.5325786548},
{"learn":[10.81941677],"iteration":83,"passed_time":0.04882036489,"remaining_time":0.5323744552},
{"learn":[10.50689209],"iteration":84,"passed_time":0.04946119748,"remaining_time":0.5324352435},
{"learn":[10.21452797],"iteration":85,"passed_time":0.04979796422,"remaining_time":0.5292481314},
{"learn":[9.927411106],"iteration":86,"passed_time":0.05039778894,"remaining_time":0.5288871414},
{"learn":[9.64693391],"iteration":87,"passed_time":0.05101685035,"remaining_time":0.5287200854},
{"learn":[9.384984105],"iteration":88,"passed_time":0.0516475604,"remaining_time":0.528662107},
{"learn":[9.134399111],"iteration":89,"passed_time":0.05224128583,"remaining_time":0.5282174457},
{"learn":[8.920082495],"iteration":90,"passed_time":0.05286010241,"remaining_time":0.5280201438},
{"learn":[8.687452491],"iteration":91,"passed_time":0.05348131909,"remaining_time":0.5278373666},
{"learn":[8.47884153],"iteration":92,"passed_time":0.05409485162,"remaining_time":0.5275702196},
{"learn":[8.267519173],"iteration":93,"passed_time":0.05468824735,"remaining_time":0.5271016181},
{"learn":[8.066316572],"iteration":94,"passed_time":0.05530411927,"remaining_time":0.5268445047},
{"learn":[7.865361633],"iteration":95,"passed_time":0.05592176115,"remaining_time":0.5265965842},
{"learn":[7.656384398],"iteration":96,"passed_time":0.05650567327,"remaining_time":0.5260270409},
{"learn":[7.476972157],"iteration":97,"passed_time":0.05713770823,"remaining_time":0.5259001309},
{"learn":[7.311775991],"iteration":98,"passed_time":0.05778128575,"remaining_time":0.5258680653},
{"learn":[7.166623308],"iteration":99,"passed_time":0.0583553548,"remaining_time":0.5251981932},
{"learn":[7.018869628],"iteration":100,"passed_time":0.05896955723,"remaining_time":0.524887445},
{"learn":[6.870082812],"iteration":101,"passed_time":0.05960225647,"remaining_time":0.5247335913},
{"learn":[6.742769252],"iteration":102,"passed_time":0.06024291957,"remaining_time":0.5246397947},
{"learn":[6.595383081],"iteration":103,"passed_time":0.06090839922,"remaining_time":0.5247492856},
{"learn":[6.436445409],"iteration":104,"passed_time":0.06135283837,"remaining_time":0.5229599081},
{"learn":[6.294743118],"iteration":105,"passed_time":0.06193130136,"remaining_time":0.5223262586},
{"learn":[6.194382647],"iteration":106,"passed_time":0.06217930269,"remaining_time":0.5189356757},
{"learn":[6.074521249],"iteration":107,"passed_time":0.06275646564,"remaining_time":0.5183219199},
{"learn":[5.959091251],"iteration":108,"passed_time":0.0634031629,"remaining_time":0.5182772307},
{"learn":[5.870241096],"iteration":109,"passed_time":0.06401073639,"remaining_time":0.5179050489},
{"learn":[5.781740151],"iteration":110,"passed_time":0.0646310276,"remaining_time":0.5176304823},
{"learn":[5.675396045],"iteration":111,"passed_time":0.06526085779,"remaining_time":0.5174253725},
{"learn":[5.586975189],"iteration":112,"passed_time":0.06586710612,"remaining_time":0.5170276383},
{"learn":[5.504782698],"iteration":113,"passed_time":0.06650386033,"remaining_time":0.5168633355},
{"learn":[5.404739114],"iteration":114,"passed_time":0.06715056223,"remaining_time":0.5167673702},
{"learn":[5.306710593],"iteration":115,"passed_time":0.06776075066,"remaining_time":0.5163836516},
{"learn":[5.203943963],"iteration":116,"passed_time":0.0682049201,"remaining_time":0.5147431149},
{"learn":[5.101218117],"iteration":117,"passed_time":0.0688511828,"remaining_time":0.5146334172},
{"learn":[5.029513653],"iteration":118,"passed_time":0.06948182188,"remaining_time":0.5143990343},
{"learn":[4.955030245],"iteration":119,"passed_time":0.07012373528,"remaining_time":0.5142407254},
{"learn":[4.870876974],"iteration":120,"passed_time":0.07073129876,"remaining_time":0.5138248893},
{"learn":[4.807195291],"iteration":121,"passed_time":0.07136099409,"remaining_time":0.513565187},
{"learn":[4.71921484],"iteration":122,"passed_time":0.07197918028,"remaining_time":0.5132174073},
{"learn":[4.634737353],"iteration":123,"passed_time":0.07255169933,"remaining_time":0.5125426501},
{"learn":[4.567496534],"iteration":124,"passed_time":0.07313294723,"remaining_time":0.5119306306},
{"learn":[4.513182976],"iteration":125,"passed_time":0.07373911094,"remaining_time":0.5114919282},
{"learn":[4.455089672],"iteration":126,"passed_time":0.07432628376,"remaining_time":0.510920045},
{"learn":[4.416826694],"iteration":127,"passed_time":0.07484613117,"remaining_time":0.5098892686},
{"learn":[4.372707153],"iteration":128,"passed_time":0.07523444949,"remaining_time":0.5079783372},
{"learn":[4.325286913],"iteration":129,"passed_time":0.07579971847,"remaining_time":0.507275039},
{"learn":[4.280803548],"iteration":130,"passed_time":0.07641103135,"remaining_time":0.5068792843},
{"learn":[4.249709472],"iteration":131,"passed_time":0.07700190749,"remaining_time":0.5063458765},
{"learn":[4.219661698],"iteration":132,"passed_time":0.07759888265,"remaining_time":0.5058513629},
{"learn":[4.153661249],"iteration":133,"passed_time":0.07819843741,"remaining_time":0.505371991},
{"learn":[4.107319167],"iteration":134,"passed_time":0.07879280299,"remaining_time":0.5048575895},
{"learn":[4.061852985],"iteration":135,"passed_time":0.07938246931,"remaining_time":0.504312158},
{"learn":[4.01604258],"iteration":136,"passed_time":0.07998202407,"remaining_time":0.5038283706},
{"learn":[3.96726929],"iteration":137,"passed_time":0.08057176038,"remaining_time":0.5032815757},
{"learn":[3.917072272],"iteration":138,"passed_time":0.08116496614,"remaining_time":0.5027556536},
{"learn":[3.868016285],"iteration":139,"passed_time":0.08170188085,"remaining_time":0.5018829824},
{"learn":[3.82022195],"iteration":140,"passed_time":0.08222062844,"remaining_time":0.500904396},
{"learn":[3.79376664],"iteration":141,"passed_time":0.08274076581,"remaining_time":0.4999406836},
{"learn":[3.749481447],"iteration":142,"passed_time":0.0832513447,"remaining_time":0.498925891},
{"learn":[3.715532621],"iteration":143,"passed_time":0.08376773267,"remaining_time":0.4979526331},
{"learn":[3.686783493],"iteration":144,"passed_time":0.0843057372,"remaining_time":0.4971131401},
{"learn":[3.658638023],"iteration":145,"passed_time":0.08482412485,"remaining_time":0.4961630317},
{"learn":[3.64381335],"iteration":146,"passed_time":0.08540991179,"remaining_time":0.4956098963},
{"learn":[3.60271912],"iteration":147,"passed_time":0.08599486009,"remaining_time":0.4950514919},
{"learn":[3.552999364],"iteration":148,"passed_time":0.08664163612,"remaining_time":0.4948458546},
{"learn":[3.514422581],"iteration":149,"passed_time":0.08724911962,"remaining_time":0.4944116778},
{"learn":[3.493776849],"iteration":150,"passed_time":0.08787553132,"remaining_time":0.4940816298},
{"learn":[3.457542993],"iteration":151,"passed_time":0.08840911656,"remaining_time":0.4932298082},
{"learn":[3.432507235],"iteration":152,"passed_time":0.08892867402,"remaining_time":0.4923044895},
{"learn":[3.401387106],"iteration":153,"passed_time":0.08945018118,"remaining_time":0.4913951511},
{"learn":[3.367898181],"iteration":154,"passed_time":0.08996981863,"remaining_time":0.4904806241},
{"learn":[3.345167321],"iteration":155,"passed_time":0.09047755797,"remaining_time":0.489506788},
{"learn":[3.323674404],"iteration":156,"passed_time":0.09098302767,"remaining_time":0.4885267027},
{"learn":[3.303148257],"iteration":157,"passed_time":0.09149621614,"remaining_time":0.4875937594},
{"learn":[3.266501084],"iteration":158,"passed_time":0.09201920306,"remaining_time":0.4867179231},
{"learn":[3.241179311],"iteration":159,"passed_time":0.09254567943,"remaining_time":0.485864817},
{"learn":[3.204077718],"iteration":160,"passed_time":0.09306186742,"remaining_time":0.4849621538},
{"learn":[3.178511191],"iteration":161,"passed_time":0.09357970516,"remaining_time":0.4840727958},
{"learn":[3.140636137],"iteration":162,"passed_time":0.09410061241,"remaining_time":0.4832037582},
{"learn":[3.11577464],"iteration":163,"passed_time":0.09462257949,"remaining_time":0.4823443686},
{"learn":[3.094862866],"iteration":164,"passed_time":0.0951424569,"remaining_time":0.481478494},
{"learn":[3.073099471],"iteration":165,"passed_time":0.09566460395,"remaining_time":0.4806281909},
{"learn":[3.050187043],"iteration":166,"passed_time":0.09618407143,"remaining_time":0.4797684521},
{"learn":[3.035732712],"iteration":167,"passed_time":0.09644591983,"remaining_time":0.4776369363},
{"learn":[3.008459428],"iteration":168,"passed_time":0.09696223781,"remaining_time":0.4767788143},
{"learn":[2.990487475],"iteration":169,"passed_time":0.0974765861,"remaining_time":0.4759150969},
{"learn":[2.970040665],"iteration":170,"passed_time":0.0980916184,"remaining_time":0.4755435769},
{"learn":[2.953140828],"iteration":171,"passed_time":0.09868832263,"remaining_time":0.475080995},
{"learn":[2.932824515],"iteration":172,"passed_time":0.09931676255,"remaining_time":0.4747685701},
{"learn":[2.918966656],"iteration":173,"passed_time":0.09989809142,"remaining_time":0.4742288708},
{"learn":[2.898820508],"iteration":174,"passed_time":0.1004130196,"remaining_time":0.4733756639},
{"learn":[2.883917539],"iteration":175,"passed_time":0.1009352167,"remaining_time":0.4725603326},
{"learn":[2.871341584],"iteration":176,"passed_time":0.1014497949,"remaining_time":0.4717128882},
{"learn":[2.854774385],"iteration":177,"passed_time":0.1019635233,"remaining_time":0.4708652593},
{"learn":[2.831851501],"iteration":178,"passed_time":0.1024923493,"remaining_time":0.4700906077},
{"learn":[2.823533283],"iteration":179,"passed_time":0.1030087273,"remaining_time":0.4692619798},
{"learn":[2.811929007],"iteration":180,"passed_time":0.1036166695,"remaining_time":0.4688511177},
{"learn":[2.791047948],"iteration":181,"passed_time":0.1042284723,"remaining_time":0.4684554413},
{"learn":[2.773430353],"iteration":182,"passed_time":0.1048293868,"remaining_time":0.4680087925},
{"learn":[2.758929797],"iteration":183,"passed_time":0.1054670067,"remaining_time":0.4677232473},
{"learn":[2.741225428],"iteration":184,"passed_time":0.1059916234,"remaining_time":0.4669360707},
{"learn":[2.725136498],"iteration":185,"passed_time":0.1065056317,"remaining_time":0.4661052916},
{"learn":[2.702956278],"iteration":186,"passed_time":0.1070177004,"remaining_time":0.4652694675},
{"learn":[2.698429716],"iteration":187,"passed_time":0.1075359181,"remaining_time":0.4644636462},
{"learn":[2.688936883],"iteration":188,"passed_time":0.108052726,"remaining_time":0.4636548189},
{"learn":[2.68120312],"iteration":189,"passed_time":0.1085655445,"remaining_time":0.4628320582},
{"learn":[2.6619152],"iteration":190,"passed_time":0.109084912,"remaining_time":0.4620402817},
{"learn":[2.645877826],"iteration":191,"passed_time":0.1096024198,"remaining_time":0.4612435166},
{"learn":[2.630719983],"iteration":192,"passed_time":0.1102511655,"remaining_time":0.4609983967},
{"learn":[2.619822105],"iteration":193,"passed_time":0.1108687186,"remaining_time":0.4606195217},
{"learn":[2.605367906],"iteration":194,"passed_time":0.1113897359,"remaining_time":0.4598396788},
{"learn":[2.592740682],"iteration":195,"passed_time":0.1119443365,"remaining_time":0.4592002376},
{"learn":[2.580063046],"iteration":196,"passed_time":0.1124835411,"remaining_time":0.4584989011},
{"learn":[2.567108276],"iteration":197,"passed_time":0.113100943,"remaining_time":0.458115941},
{"learn":[2.555324183],"iteration":198,"passed_time":0.1136975292,"remaining_time":0.4576468388},
{"learn":[2.545052367],"iteration":199,"passed_time":0.1142147171,"remaining_time":0.4568588683},
{"learn":[2.535485579],"iteration":200,"passed_time":0.1147321049,"remaining_time":0.4560743871},
{"learn":[2.524824278],"iteration":201,"passed_time":0.115247803,"remaining_time":0.4552858751},
{"learn":[2.511830307],"iteration":202,"passed_time":0.1157631511,"remaining_time":0.454498677},
{"learn":[2.501576004],"iteration":203,"passed_time":0.1162814388,"remaining_time":0.453725614},
{"learn":[2.491310384],"iteration":204,"passed_time":0.1167993165,"remaining_time":0.4529534469},
{"learn":[2.482883087],"iteration":205,"passed_time":0.1173239632,"remaining_time":0.4522098386},
{"learn":[2.472897561],"iteration":206,"passed_time":0.1178444605,"remaining_time":0.45145245},
{"learn":[2.463937565],"iteration":207,"passed_time":0.1183782644,"remaining_time":0.4507480069},
{"learn":[2.453005579],"iteration":208,"passed_time":0.1188925228,"remaining_time":0.4499712225},
{"learn":[2.444954422],"iteration":209,"passed_time":0.119407311,"remaining_time":0.4491989317},
{"learn":[2.436167968],"iteration":210,"passed_time":0.1199282082,"remaining_time":0.4484519255},
{"learn":[2.422381249],"iteration":211,"passed_time":0.1204493654,"remaining_time":0.4477080187},
{"learn":[2.4094028],"iteration":212,"passed_time":0.1209803511,"remaining_time":0.4470025178},
{"learn":[2.394551199],"iteration":213,"passed_time":0.1215015783,"remaining_time":0.4462628062},
{"learn":[2.383760497],"iteration":214,"passed_time":0.1221259091,"remaining_time":0.4459015751},
{"learn":[2.37021808],"iteration":215,"passed_time":0.1227359022,"remaining_time":0.4454858672},
{"learn":[2.362114712],"iteration":216,"passed_time":0.1233408061,"remaining_time":0.4450500054},
{"learn":[2.354366957],"iteration":217,"passed_time":0.1239363515,"remaining_time":0.4445790223},
{"learn":[2.342820137],"iteration":218,"passed_time":0.124576321,"remaining_time":0.4442653276},
{"learn":[2.331499995],"iteration":219,"passed_time":0.1251886638,"remaining_time":0.443850717},
{"learn":[2.32868211],"iteration":220,"passed_time":0.1257784801,"remaining_time":0.4433549139},
{"learn":[2.321456163],"iteration":221,"passed_time":0.1266897653,"remaining_time":0.4439848532},
{"learn":[2.313652033],"iteration":222,"passed_time":0.1272779755,"remaining_time":0.4434752779},
{"learn":[2.307029415],"iteration":223,"passed_time":0.1278072514,"remaining_time":0.4427608353},
{"learn":[2.30316725],"iteration":224,"passed_time":0.1283652028,"remaining_time":0.4421468096},
{"learn":[2.300585277],"iteration":225,"passed_time":0.1288943387,"remaining_time":0.4414345937},
{"learn":[2.290943516],"iteration":226,"passed_time":0.1294218049,"remaining_time":0.440718305},
{"learn":[2.280446248],"iteration":227,"passed_time":0.1299530506,"remaining_time":0.4400164694},
{"learn":[2.270658033],"iteration":228,"passed_time":0.1305131516,"remaining_time":0.4394132745},
{"learn":[2.268139671],"iteration":229,"passed_time":0.1311754859,"remaining_time":0.4391527136},
{"learn":[2.266221372],"iteration":230,"passed_time":0.1316920138,"remaining_time":0.4384032841},
{"learn":[2.260614367],"iteration":231,"passed_time":0.1322421476,"remaining_time":0.4377671094},
{"learn":[2.253313692],"iteration":232,"passed_time":0.1327773626,"remaining_time":0.4370825628},
{"learn":[2.246355853],"iteration":233,"passed_time":0.133328735,"remaining_time":0.4364521839},
{"learn":[2.239676465],"iteration":234,"passed_time":0.1338915856,"remaining_time":0.4358598425},
{"learn":[2.232300932],"iteration":235,"passed_time":0.1344168722,"remaining_time":0.4351461455},
{"learn":[2.222560287],"iteration":236,"passed_time":0.1349429086,"remaining_time":0.4344364526},
{"learn":[2.219570237],"iteration":237,"passed_time":0.1354615162,"remaining_time":0.4337045183},
{"learn":[2.209531358],"iteration":238,"passed_time":0.1359881326,"remaining_time":0.4329998698},
{"learn":[2.200912629],"iteration":239,"passed_time":0.1365086299,"remaining_time":0.4322773279},
{"learn":[2.196547155],"iteration":240,"passed_time":0.1370378458,"remaining_time":0.431583921},
{"learn":[2.193883726],"iteration":241,"passed_time":0.1378093271,"remaining_time":0.4316507024},
{"learn":[2.191439526],"iteration":242,"passed_time":0.1383476516,"remaining_time":0.4309842481},
{"learn":[2.190214196],"iteration":243,"passed_time":0.1388695687,"remaining_time":0.430268008},
{"learn":[2.187132183],"iteration":244,"passed_time":0.1393927056,"remaining_time":0.4295571132},
{"learn":[2.175868552],"iteration":245,"passed_time":0.1399178822,"remaining_time":0.4288539966},
{"learn":[2.166448275],"iteration":246,"passed_time":0.1406005798,"remaining_time":0.4286325369},
{"learn":[2.16245618],"iteration":247,"passed_time":0.1412571155,"remaining_time":0.4283280277},
{"learn":[2.159407363],"iteration":248,"passed_time":0.1418828461,"remaining_time":0.4279277809},
{"learn":[2.154385625],"iteration":249,"passed_time":0.1424697129,"remaining_time":0.4274091387},
{"learn":[2.150687506],"iteration":250,"passed_time":0.1431505635,"remaining_time":0.4271704067},
{"learn":[2.138722959],"iteration":251,"passed_time":0.1440266543,"remaining_time":0.4275076883},
{"learn":[2.135145193],"iteration":252,"passed_time":0.1448062305,"remaining_time":0.4275504118},
{"learn":[2.13222478],"iteration":253,"passed_time":0.1455285957,"remaining_time":0.4274186316},
{"learn":[2.125725824],"iteration":254,"passed_time":0.1461933201,"remaining_time":0.4271138177},
{"learn":[2.123496097],"iteration":255,"passed_time":0.146829769,"remaining_time":0.4267240163},
{"learn":[2.114601294],"iteration":256,"passed_time":0.147492595,"remaining_time":0.4264085527},
{"learn":[2.112966465],"iteration":257,"passed_time":0.1481649781,"remaining_time":0.4261178829},
{"learn":[2.109757019],"iteration":258,"passed_time":0.1488536787,"remaining_time":0.4258709496},
{"learn":[2.107901534],"iteration":259,"passed_time":0.149549327,"remaining_time":0.4256403922},
{"learn":[2.105195419],"iteration":260,"passed_time":0.1502959396,"remaining_time":0.4255505723},
{"learn":[2.10431213],"iteration":261,"passed_time":0.1509922578,"remaining_time":0.4253140696},
{"learn":[2.097992824],"iteration":262,"passed_time":0.1516039106,"remaining_time":0.4248368142},
{"learn":[2.097021722],"iteration":263,"passed_time":0.1522083658,"remaining_time":0.4243384744},
{"learn":[2.090831069],"iteration":264,"passed_time":0.1527412612,"remaining_time":0.4236408564},
{"learn":[2.089848151],"iteration":265,"passed_time":0.1532566693,"remaining_time":0.4228962227},
{"learn":[2.088986254],"iteration":266,"passed_time":0.1537750469,"remaining_time":0.4221614584},
{"learn":[2.088067521],"iteration":267,"passed_time":0.1542904451,"remaining_time":0.4214201708},
{"learn":[2.085309745],"iteration":268,"passed_time":0.1548113723,"remaining_time":0.4206955879},
{"learn":[2.076631523],"iteration":269,"passed_time":0.1553339393,"remaining_time":0.4199769469},
{"learn":[2.075993119],"iteration":270,"passed_time":0.1559095166,"remaining_time":0.4194023528},
{"learn":[2.075222203],"iteration":271,"passed_time":0.1565249289,"remaining_time":0.4189343684},
{"learn":[2.072655364],"iteration":272,"passed_time":0.1571162649,"remaining_time":0.418401189},
{"learn":[2.069956549],"iteration":273,"passed_time":0.1577129301,"remaining_time":0.4178817054},
{"learn":[2.067312303],"iteration":274,"passed_time":0.158349769,"remaining_time":0.4174675727},
{"learn":[2.066559848],"iteration":275,"passed_time":0.1589546129,"remaining_time":0.4169678976},
{"learn":[2.062818225],"iteration":276,"passed_time":0.1595529378,"remaining_time":0.4164504478},
{"learn":[2.060213838],"iteration":277,"passed_time":0.1601514628,"remaining_time":0.4159329356},
{"learn":[2.059533417],"iteration":278,"passed_time":0.1607426188,"remaining_time":0.4153957999},
{"learn":[2.058886053],"iteration":279,"passed_time":0.1613337549,"remaining_time":0.414858227},
{"learn":[2.056354502],"iteration":280,"passed_time":0.1619264508,"remaining_time":0.4143242637},
{"learn":[2.055778312],"iteration":281,"passed_time":0.1625137275,"remaining_time":0.4137760863},
{"learn":[2.053300455],"iteration":282,"passed_time":0.1631144021,"remaining_time":0.4132615769},
{"learn":[2.050827664],"iteration":283,"passed_time":0.1637070979,"remaining_time":0.4127263454},
{"learn":[2.042462702],"iteration":284,"passed_time":0.1643077425,"remaining_time":0.4122106522},
{"learn":[2.039398929],"iteration":285,"passed_time":0.1649062974,"remaining_time":0.4116891481},
{"learn":[2.032075449],"iteration":286,"passed_time":0.1655011929,"remaining_time":0.4111580158},
{"learn":[2.029596534],"iteration":287,"passed_time":0.1661002177,"remaining_time":0.4106366494},
{"learn":[2.027164418],"iteration":288,"passed_time":0.1666681475,"remaining_time":0.4100382453},
{"learn":[2.019246364],"iteration":289,"passed_time":0.1671885648,"remaining_time":0.4093237277},
{"learn":[2.016911038],"iteration":290,"passed_time":0.1677541301,"remaining_time":0.4087205438},
{"learn":[2.011284221],"iteration":291,"passed_time":0.1682911848,"remaining_time":0.4080484892},
{"learn":[2.009035639],"iteration":292,"passed_time":0.1689979179,"remaining_time":0.4077867848},
{"learn":[2.001493838],"iteration":293,"passed_time":0.1696230793,"remaining_time":0.40732617},
{"learn":[1.999275842],"iteration":294,"passed_time":0.1701512154,"remaining_time":0.4066325656},
{"learn":[1.987534969],"iteration":295,"passed_time":0.1706858405,"remaining_time":0.4059555125},
{"learn":[1.984728687],"iteration":296,"passed_time":0.171223765,"remaining_time":0.4052872283},
{"learn":[1.984107932],"iteration":297,"passed_time":0.1717370835,"remaining_time":0.4045618544},
{"learn":[1.98083768],"iteration":298,"passed_time":0.1722645997,"remaining_time":0.4038711852},
{"learn":[1.975489597],"iteration":299,"passed_time":0.1727893663,"remaining_time":0.4031751881},
{"learn":[1.972315829],"iteration":300,"passed_time":0.1733096037,"remaining_time":0.4024698105},
{"learn":[1.97171357],"iteration":301,"passed_time":0.1738166731,"remaining_time":0.4017352246},
{"learn":[1.969671767],"iteration":302,"passed_time":0.1743306515,"remaining_time":0.4010180332},
{"learn":[1.969087154],"iteration":303,"passed_time":0.1748460596,"remaining_time":0.4003054522},
{"learn":[1.961833984],"iteration":304,"passed_time":0.175366057,"remaining_time":0.3996046216},
{"learn":[1.959224036],"iteration":305,"passed_time":0.1758805552,"remaining_time":0.3988925011},
{"learn":[1.95866414],"iteration":306,"passed_time":0.1763924339,"remaining_time":0.3981757548},
{"learn":[1.95668157],"iteration":307,"passed_time":0.1769560832,"remaining_time":0.3975766544},
{"learn":[1.954166904],"iteration":308,"passed_time":0.1775008866,"remaining_time":0.3969356397},
{"learn":[1.953579949],"iteration":309,"passed_time":0.1780204041,"remaining_time":0.396238964},
{"learn":[1.950572655],"iteration":310,"passed_time":0.178543281,"remaining_time":0.3955508702},
{"learn":[1.948145352],"iteration":311,"passed_time":0.1790649382,"remaining_time":0.3948611457},
{"learn":[1.936901126],"iteration":312,"passed_time":0.1796200412,"remaining_time":0.3942459051},
{"learn":[1.92954626],"iteration":313,"passed_time":0.1801651646,"remaining_time":0.3936092449},
{"learn":[1.922551703],"iteration":314,"passed_time":0.1806954903,"remaining_time":0.392940987},
{"learn":[1.922074425],"iteration":315,"passed_time":0.1812112384,"remaining_time":0.3922420477},
{"learn":[1.91714437],"iteration":316,"passed_time":0.1817503728,"remaining_time":0.3915946517},
{"learn":[1.912554724],"iteration":317,"passed_time":0.1823885602,"remaining_time":0.3911603712},
{"learn":[1.903350219],"iteration":318,"passed_time":0.1830389781,"remaining_time":0.3907509218},
{"learn":[1.892856969],"iteration":319,"passed_time":0.1837092016,"remaining_time":0.3903820534},
{"learn":[1.888162323],"iteration":320,"passed_time":0.1843196446,"remaining_time":0.3898848557},
{"learn":[1.878084839],"iteration":321,"passed_time":0.1849552024,"remaining_time":0.3894398362},
{"learn":[1.871436808],"iteration":322,"passed_time":0.1856296253,"remaining_time":0.389075097},
{"learn":[1.867129003],"iteration":323,"passed_time":0.1863260959,"remaining_time":0.3887544469},
{"learn":[1.85759219],"iteration":324,"passed_time":0.1869952184,"remaining_time":0.3883746843},
{"learn":[1.85308034],"iteration":325,"passed_time":0.1876916989,"remaining_time":0.3880497088},
{"learn":[1.852050812],"iteration":326,"passed_time":0.1884612655,"remaining_time":0.3878728797},
{"learn":[1.845807309],"iteration":327,"passed_time":0.1891099736,"remaining_time":0.387444824},
{"learn":[1.84169973],"iteration":328,"passed_time":0.189768619,"remaining_time":0.3870356941},
{"learn":[1.840731713],"iteration":329,"passed_time":0.1904690665,"remaining_time":0.3867099229},
{"learn":[1.840195773],"iteration":330,"passed_time":0.1911632662,"remaining_time":0.3863692601},
{"learn":[1.832124709],"iteration":331,"passed_time":0.1918103246,"remaining_time":0.3859316171},
{"learn":[1.823147206],"iteration":332,"passed_time":0.1924724195,"remaining_time":0.3855228342},
{"learn":[1.819916077],"iteration":333,"passed_time":0.19309829,"remaining_time":0.3850403029},
{"learn":[1.816285512],"iteration":334,"passed_time":0.1937739215,"remaining_time":0.3846556949},
{"learn":[1.813135016],"iteration":335,"passed_time":0.1944498641,"remaining_time":0.3842699696},
{"learn":[1.811996615],"iteration":336,"passed_time":0.1951120301,"remaining_time":0.3838554183},
{"learn":[1.81148793],"iteration":337,"passed_time":0.195753477,"remaining_time":0.3833988219},
{"learn":[1.8072091],"iteration":338,"passed_time":0.1963693792,"remaining_time":0.3828913264},
{"learn":[1.804133855],"iteration":339,"passed_time":0.1969452477,"remaining_time":0.3823054808},
{"learn":[1.800154123],"iteration":340,"passed_time":0.1975819665,"remaining_time":0.3818372902},
{"learn":[1.79706832],"iteration":341,"passed_time":0.1981872104,"remaining_time":0.3813075568},
{"learn":[1.794967584],"iteration":342,"passed_time":0.1987905246,"remaining_time":0.380773687},
{"learn":[1.792303236],"iteration":343,"passed_time":0.1993887895,"remaining_time":0.3802297847},
{"learn":[1.787498544],"iteration":344,"passed_time":0.1999841649,"remaining_time":0.3796800813},
{"learn":[1.7837272],"iteration":345,"passed_time":0.2005793804,"remaining_time":0.3791298115},
{"learn":[1.783236595],"iteration":346,"passed_time":0.2011716263,"remaining_time":0.3785736944},
{"learn":[1.782767674],"iteration":347,"passed_time":0.201758693,"remaining_time":0.3780076663},
{"learn":[1.780263504],"iteration":348,"passed_time":0.2023488793,"remaining_time":0.3774473364},
{"learn":[1.77782405],"iteration":349,"passed_time":0.2029450546,"remaining_time":0.3768979585},
{"learn":[1.777383371],"iteration":350,"passed_time":0.2035296217,"remaining_time":0.3763268504},
{"learn":[1.772946872],"iteration":351,"passed_time":0.2041245072,"remaining_time":0.375774661},
{"learn":[1.767237394],"iteration":352,"passed_time":0.2046855693,"remaining_time":0.3751602361},
{"learn":[1.764897806],"iteration":353,"passed_time":0.2052088162,"remaining_time":0.3744771052},
{"learn":[1.759390085],"iteration":354,"passed_time":0.2057254241,"remaining_time":0.3737828128},
{"learn":[1.756011874],"iteration":355,"passed_time":0.2062463913,"remaining_time":0.3730974046},
{"learn":[1.75311621],"iteration":356,"passed_time":0.2067593998,"remaining_time":0.3723985829},
{"learn":[1.744486275],"iteration":357,"passed_time":0.2072866161,"remaining_time":0.371726278},
{"learn":[1.741479001],"iteration":358,"passed_time":0.2078148922,"remaining_time":0.3710566738},
{"learn":[1.736174419],"iteration":359,"passed_time":0.208338299,"remaining_time":0.3703791983},
{"learn":[1.734600108],"iteration":360,"passed_time":0.2088581164,"remaining_time":0.3696962227},
{"learn":[1.733444058],"iteration":361,"passed_time":0.2093733446,"remaining_time":0.3690060604},
{"learn":[1.733081364],"iteration":362,"passed_time":0.2098855332,"remaining_time":0.368311528},
{"learn":[1.730141097],"iteration":363,"passed_time":0.2104101799,"remaining_time":0.3676397648},
{"learn":[1.727552572],"iteration":364,"passed_time":0.2109259079,"remaining_time":0.3669532919},
{"learn":[1.726025977],"iteration":365,"passed_time":0.211447875,"remaining_time":0.3662785595},
{"learn":[1.725135827],"iteration":366,"passed_time":0.2119604236,"remaining_time":0.3655884146},
{"learn":[1.722926406],"iteration":367,"passed_time":0.2124784413,"remaining_time":0.3649086275},
{"learn":[1.72158821],"iteration":368,"passed_time":0.2129879404,"remaining_time":0.3642151501},
{"learn":[1.720495431],"iteration":369,"passed_time":0.2135023387,"remaining_time":0.3635310091},
{"learn":[1.71532125],"iteration":370,"passed_time":0.2140175468,"remaining_time":0.3628491562},
{"learn":[1.713880184],"iteration":371,"passed_time":0.2145348346,"remaining_time":0.3621717101},
{"learn":[1.712342767],"iteration":372,"passed_time":0.2150501228,"remaining_time":0.3614917613},
{"learn":[1.710198096],"iteration":373,"passed_time":0.2155668107,"remaining_time":0.3608150361},
{"learn":[1.70868761],"iteration":374,"passed_time":0.2160883278,"remaining_time":0.3601472131},
{"learn":[1.707286617],"iteration":375,"passed_time":0.2166044059,"remaining_time":0.3594711416},
{"learn":[1.704618317],"iteration":376,"passed_time":0.2171299424,"remaining_time":0.3588115493},
{"learn":[1.702554869],"iteration":377,"passed_time":0.2176407112,"remaining_time":0.3581283661},
{"learn":[1.701495918],"iteration":378,"passed_time":0.2181596288,"remaining_time":0.3574594446},
{"learn":[1.694641925],"iteration":379,"passed_time":0.2186754669,"remaining_time":0.356786288},
{"learn":[1.68972633],"iteration":380,"passed_time":0.2191949943,"remaining_time":0.3561199514},
{"learn":[1.689024929],"iteration":381,"passed_time":0.2197119922,"remaining_time":0.355450291},
{"learn":[1.684300269],"iteration":382,"passed_time":0.2202664229,"remaining_time":0.3548417309},
{"learn":[1.682808732],"iteration":383,"passed_time":0.220782201,"remaining_time":0.3541714474},
{"learn":[1.681481663],"iteration":384,"passed_time":0.2212964293,"remaining_time":0.3534994909},
{"learn":[1.681159119],"iteration":385,"passed_time":0.2218068182,"remaining_time":0.3528222445},
{"learn":[1.680072793],"iteration":386,"passed_time":0.2223137977,"remaining_time":0.3521404598},
{"learn":[1.678787133],"iteration":387,"passed_time":0.2228260363,"remaining_time":0.3514678717},
{"learn":[1.677271535],"iteration":388,"passed_time":0.2233413544,"remaining_time":0.3508009449},
{"learn":[1.675181821],"iteration":389,"passed_time":0.2238616918,"remaining_time":0.3501426461},
{"learn":[1.674864127],"iteration":390,"passed_time":0.2243680213,"remaining_time":0.3494632352},
{"learn":[1.674557888],"iteration":391,"passed_time":0.2250268966,"remaining_time":0.3490213091},
{"learn":[1.673132451],"iteration":392,"passed_time":0.2256408291,"remaining_time":0.3485088633},
{"learn":[1.670480723],"iteration":393,"passed_time":0.2262415837,"remaining_time":0.3479756338},
{"learn":[1.667989424],"iteration":394,"passed_time":0.2267896866,"remaining_time":0.3473614187},
{"learn":[1.6669567],"iteration":395,"passed_time":0.2273126035,"remaining_time":0.3467091226},
{"learn":[1.66160595],"iteration":396,"passed_time":0.2278425594,"remaining_time":0.3460681695},
{"learn":[1.653867288],"iteration":397,"passed_time":0.228361117,"remaining_time":0.3454105337},
{"learn":[1.648685967],"iteration":398,"passed_time":0.2288762851,"remaining_time":0.3447484896},
{"learn":[1.647266336],"iteration":399,"passed_time":0.2293921832,"remaining_time":0.3440882748},
{"learn":[1.646965734],"iteration":400,"passed_time":0.2299001725,"remaining_time":0.3434169659},
{"learn":[1.646675945],"iteration":401,"passed_time":0.2304125011,"remaining_time":0.3427529245},
{"learn":[1.645683268],"iteration":402,"passed_time":0.230929329,"remaining_time":0.3420963013},
{"learn":[1.644287916],"iteration":403,"passed_time":0.2314445571,"remaining_time":0.34143801},
{"learn":[1.643059847],"iteration":404,"passed_time":0.231991649,"remaining_time":0.3408272374},
{"learn":[1.640624585],"iteration":405,"passed_time":0.2325910938,"remaining_time":0.3402933737},
{"learn":[1.639314106],"iteration":406,"passed_time":0.2331857593,"remaining_time":0.3397522243},
{"learn":[1.63630537],"iteration":407,"passed_time":0.2337800749,"remaining_time":0.3392103048},
{"learn":[1.63118348],"iteration":408,"passed_time":0.2343812494,"remaining_time":0.3386780401},
{"learn":[1.630910603],"iteration":409,"passed_time":0.2349665964,"remaining_time":0.3381226631},
{"learn":[1.629527791],"iteration":410,"passed_time":0.2355621318,"remaining_time":0.3375817412},
{"learn":[1.629379708],"iteration":411,"passed_time":0.2360718308,"remaining_time":0.3369180498},
{"learn":[1.62802186],"iteration":412,"passed_time":0.2365912683,"remaining_time":0.3362689455},
{"learn":[1.620558361],"iteration":413,"passed_time":0.2371035669,"remaining_time":0.3356103629},
{"learn":[1.612615356],"iteration":414,"passed_time":0.2376243142,"remaining_time":0.3349643947},
{"learn":[1.610212725],"iteration":415,"passed_time":0.2381313037,"remaining_time":0.3342997148},
{"learn":[1.609204674],"iteration":416,"passed_time":0.2386432923,"remaining_time":0.3336427804},
{"learn":[1.608478781],"iteration":417,"passed_time":0.2391796671,"remaining_time":0.3330204935},
{"learn":[1.603512171],"iteration":418,"passed_time":0.2398322934,"remaining_time":0.332559815},
{"learn":[1.602334035],"iteration":419,"passed_time":0.2404248793,"remaining_time":0.3320153095},
{"learn":[1.600979451],"iteration":420,"passed_time":0.2410197848,"remaining_time":0.3314737658},
{"learn":[1.59957564],"iteration":421,"passed_time":0.2416106909,"remaining_time":0.3309264914},
{"learn":[1.598579753],"iteration":422,"passed_time":0.2422068962,"remaining_time":0.330386239},
{"learn":[1.597247746],"iteration":423,"passed_time":0.2427943029,"remaining_time":0.32983377},
{"learn":[1.595901985],"iteration":424,"passed_time":0.243328668,"remaining_time":0.3292093744},
{"learn":[1.595280004],"iteration":425,"passed_time":0.2438375472,"remaining_time":0.3285510612},
{"learn":[1.590381431],"iteration":426,"passed_time":0.2443536252,"remaining_time":0.3279031083},
{"learn":[1.587561056],"iteration":427,"passed_time":0.2448805815,"remaining_time":0.3272703098},
{"learn":[1.587430378],"iteration":428,"passed_time":0.2453891707,"remaining_time":0.3266135582},
{"learn":[1.584499514],"iteration":429,"passed_time":0.2459027091,"remaining_time":0.3259640562},
{"learn":[1.583205562],"iteration":430,"passed_time":0.2464173074,"remaining_time":0.3253165844},
{"learn":[1.582965433],"iteration":431,"passed_time":0.2469277463,"remaining_time":0.324664259},
{"learn":[1.581999951],"iteration":432,"passed_time":0.2474420346,"remaining_time":0.3240176296},
{"learn":[1.577167035],"iteration":433,"passed_time":0.2479578826,"remaining_time":0.3233736441},
{"learn":[1.576898626],"iteration":434,"passed_time":0.2484664118,"remaining_time":0.3227207418},
{"learn":[1.57215515],"iteration":435,"passed_time":0.2489834597,"remaining_time":0.3220795213},
{"learn":[1.571031554],"iteration":436,"passed_time":0.2494880095,"remaining_time":0.3214227674},
{"learn":[1.568372848],"iteration":437,"passed_time":0.249995239,"remaining_time":0.3207701468},
{"learn":[1.567089774],"iteration":438,"passed_time":0.2505636474,"remaining_time":0.3201963695},
{"learn":[1.566967187],"iteration":439,"passed_time":0.2510939432,"remaining_time":0.3195741095},
{"learn":[1.564351711],"iteration":440,"passed_time":0.25161739,"remaining_time":0.3189435851},
{"learn":[1.56178121],"iteration":441,"passed_time":0.2522094672,"remaining_time":0.3184001871},
{"learn":[1.56045171],"iteration":442,"passed_time":0.2527308644,"remaining_time":0.3177677008},
{"learn":[1.55939483],"iteration":443,"passed_time":0.2533529443,"remaining_time":0.3172617952},
{"learn":[1.558127748],"iteration":444,"passed_time":0.2539728271,"remaining_time":0.316752627},
{"learn":[1.556883649],"iteration":445,"passed_time":0.2544973338,"remaining_time":0.3161244908},
{"learn":[1.55434966],"iteration":446,"passed_time":0.2550171312,"remaining_time":0.3154909923},
{"learn":[1.553383045],"iteration":447,"passed_time":0.2555334392,"remaining_time":0.3148537018},
{"learn":[1.552159022],"iteration":448,"passed_time":0.2560523067,"remaining_time":0.3142200913},
{"learn":[1.545070765],"iteration":449,"passed_time":0.2565654652,"remaining_time":0.313580013},
{"learn":[1.542564284],"iteration":450,"passed_time":0.257082813,"remaining_time":0.3129455972},
{"learn":[1.541527936],"iteration":451,"passed_time":0.2575956416,"remaining_time":0.3123062203},
{"learn":[1.539312805],"iteration":452,"passed_time":0.2581126594,"remaining_time":0.3116724607},
{"learn":[1.531890785],"iteration":453,"passed_time":0.2586357363,"remaining_time":0.3110465023},
{"learn":[1.530120277],"iteration":454,"passed_time":0.2591472051,"remaining_time":0.3104070918},
{"learn":[1.525460489],"iteration":455,"passed_time":0.2597237223,"remaining_time":0.3098458441},
{"learn":[1.524497685],"iteration":456,"passed_time":0.2603142285,"remaining_time":0.3093011511},
{"learn":[1.523274517],"iteration":457,"passed_time":0.2608405449,"remaining_time":0.3086802954},
{"learn":[1.518694813],"iteration":458,"passed_time":0.2613581526,"remaining_time":0.3080495873},
{"learn":[1.517695824],"iteration":459,"passed_time":0.2618748106,"remaining_time":0.3074182559},
{"learn":[1.516489733],"iteration":460,"passed_time":0.2623871492,"remaining_time":0.3067823718},
{"learn":[1.515305491],"iteration":461,"passed_time":0.2628905492,"remaining_time":0.3061366136},
{"learn":[1.513140363],"iteration":462,"passed_time":0.2634049575,"remaining_time":0.3055042379},
{"learn":[1.511172252],"iteration":463,"passed_time":0.263917956,"remaining_time":0.3048707423},
{"learn":[1.506655496],"iteration":464,"passed_time":0.2644323243,"remaining_time":0.3042393408},
{"learn":[1.505486193],"iteration":465,"passed_time":0.2650215007,"remaining_time":0.303694166},
{"learn":[1.504510599],"iteration":466,"passed_time":0.265610867,"remaining_time":0.3031490196},
{"learn":[1.502526721],"iteration":467,"passed_time":0.266202563,"remaining_time":0.3026063324},
{"learn":[1.495814699],"iteration":468,"passed_time":0.2668095478,"remaining_time":0.3020807461},
{"learn":[1.491426443],"iteration":469,"passed_time":0.2674012438,"remaining_time":0.3015375728},
{"learn":[1.490207447],"iteration":470,"passed_time":0.2679963593,"remaining_time":0.3009980341},
{"learn":[1.48777024],"iteration":471,"passed_time":0.2686105605,"remaining_time":0.3004796101},
{"learn":[1.485375013],"iteration":472,"passed_time":0.2692108951,"remaining_time":0.2999453314},
{"learn":[1.484210389],"iteration":473,"passed_time":0.2698019812,"remaining_time":0.2994005108},
{"learn":[1.481854486],"iteration":474,"passed_time":0.2703958769,"remaining_time":0.2988586008},
{"learn":[1.479827178],"iteration":475,"passed_time":0.2709908424,"remaining_time":0.29831765},
{"learn":[1.478680024],"iteration":476,"passed_time":0.2715891973,"remaining_time":0.2977801891},
{"learn":[1.477553696],"iteration":477,"passed_time":0.2721833629,"remaining_time":0.2972378984},
{"learn":[1.475555661],"iteration":478,"passed_time":0.2727002508,"remaining_time":0.2966113375},
{"learn":[1.474611753],"iteration":479,"passed_time":0.2732119395,"remaining_time":0.2959796012},
{"learn":[1.473503849],"iteration":480,"passed_time":0.2737202888,"remaining_time":0.2953447607},
{"learn":[1.473363773],"iteration":481,"passed_time":0.274229018,"remaining_time":0.2947108533},
{"learn":[1.47215795],"iteration":482,"passed_time":0.274738877,"remaining_time":0.2940786737},
{"learn":[1.465181098],"iteration":483,"passed_time":0.2752580645,"remaining_time":0.2934569448},
{"learn":[1.463100631],"iteration":484,"passed_time":0.2757786918,"remaining_time":0.2928371676},
{"learn":[1.461986425],"iteration":485,"passed_time":0.2762926601,"remaining_time":0.2922107558},
{"learn":[1.461053314],"iteration":486,"passed_time":0.2768130375,"remaining_time":0.2915915569},
{"learn":[1.456694783],"iteration":487,"passed_time":0.277332195,"remaining_time":0.2909714833},
{"learn":[1.455614634],"iteration":488,"passed_time":0.277936299,"remaining_time":0.2904405906},
{"learn":[1.454458414],"iteration":489,"passed_time":0.278521866,"remaining_time":0.2898901054},
{"learn":[1.453396722],"iteration":490,"passed_time":0.2791182113,"remaining_time":0.2893506508},
{"learn":[1.452476781],"iteration":491,"passed_time":0.2797066678,"remaining_time":0.2888028196},
{"learn":[1.450248613],"iteration":492,"passed_time":0.2802981538,"remaining_time":0.2882579391},
{"learn":[1.449358673],"iteration":493,"passed_time":0.280882621,"remaining_time":0.2877056806},
{"learn":[1.445059644],"iteration":494,"passed_time":0.2814752968,"remaining_time":0.2871616665},
{"learn":[1.444043414],"iteration":495,"passed_time":0.2820868797,"remaining_time":0.2866366681},
{"learn":[1.44313405],"iteration":496,"passed_time":0.2826819851,"remaining_time":0.2860946449},
{"learn":[1.442884941],"iteration":497,"passed_time":0.2832666622,"remaining_time":0.2855418965},
{"learn":[1.441856408],"iteration":498,"passed_time":0.2838630775,"remaining_time":0.2850008053},
{"learn":[1.439616109],"iteration":499,"passed_time":0.2844663517,"remaining_time":0.2844663517},
{"learn":[1.43856823],"iteration":500,"passed_time":0.2850555681,"remaining_time":0.2839176217},
{"learn":[1.437675118],"iteration":501,"passed_time":0.2856492438,"remaining_time":0.2833731542},
{"learn":[1.433433873],"iteration":502,"passed_time":0.2862410497,"remaining_time":0.2828266436},
{"learn":[1.431222609],"iteration":503,"passed_time":0.2868346754,"remaining_time":0.2822817441},
{"learn":[1.429421063],"iteration":504,"passed_time":0.2874573516,"remaining_time":0.2817651269},
{"learn":[1.423021443],"iteration":505,"passed_time":0.2879892671,"remaining_time":0.2811594821},
{"learn":[1.420866147],"iteration":506,"passed_time":0.2885097045,"remaining_time":0.2805429671},
{"learn":[1.419906102],"iteration":507,"passed_time":0.2890753307,"remaining_time":0.2799705959},
{"learn":[1.418880984],"iteration":508,"passed_time":0.2896073062,"remaining_time":0.2793657905},
{"learn":[1.417874502],"iteration":509,"passed_time":0.2901297932,"remaining_time":0.2787521542},
{"learn":[1.41688632],"iteration":510,"passed_time":0.290647281,"remaining_time":0.2781340908},
{"learn":[1.41274568],"iteration":511,"passed_time":0.291163409,"remaining_time":0.2775151242},
{"learn":[1.408682116],"iteration":512,"passed_time":0.2917130517,"remaining_time":0.2769283746},
{"learn":[1.406546448],"iteration":513,"passed_time":0.2922261802,"remaining_time":0.2763072443},
{"learn":[1.404447792],"iteration":514,"passed_time":0.2927414683,"remaining_time":0.2756885672},
{"learn":[1.403667623],"iteration":515,"passed_time":0.2932565765,"remaining_time":0.2750701221},
{"learn":[1.401738238],"iteration":516,"passed_time":0.2937750141,"remaining_time":0.2744551873},
{"learn":[1.399671859],"iteration":517,"passed_time":0.2942896124,"remaining_time":0.2738370524},
{"learn":[1.398689177],"iteration":518,"passed_time":0.2948028408,"remaining_time":0.2732180471},
{"learn":[1.397805271],"iteration":519,"passed_time":0.2953143196,"remaining_time":0.2725978335},
{"learn":[1.395771636],"iteration":520,"passed_time":0.2959599758,"remaining_time":0.2721013981},
{"learn":[1.39480497],"iteration":521,"passed_time":0.2966794927,"remaining_time":0.2716720259},
{"learn":[1.393144625],"iteration":522,"passed_time":0.2973129721,"remaining_time":0.271163074},
{"learn":[1.391172916],"iteration":523,"passed_time":0.297911197,"remaining_time":0.2706216217},
{"learn":[1.384679628],"iteration":524,"passed_time":0.2985137413,"remaining_time":0.2700838612},
{"learn":[1.383604081],"iteration":525,"passed_time":0.2991092367,"remaining_time":0.2695395023},
{"learn":[1.382835494],"iteration":526,"passed_time":0.2996975933,"remaining_time":0.268988542},
{"learn":[1.381251793],"iteration":527,"passed_time":0.3002565545,"remaining_time":0.2684111623},
{"learn":[1.380296595],"iteration":528,"passed_time":0.300769313,"remaining_time":0.2677927154},
{"learn":[1.380050061],"iteration":529,"passed_time":0.3012766124,"remaining_time":0.2671698261},
{"learn":[1.379170522],"iteration":530,"passed_time":0.3017911707,"remaining_time":0.2665537835},
{"learn":[1.378253582],"iteration":531,"passed_time":0.3023035993,"remaining_time":0.265936249},
{"learn":[1.377310338],"iteration":532,"passed_time":0.3028224268,"remaining_time":0.2653247155},
{"learn":[1.371545831],"iteration":533,"passed_time":0.3033675103,"remaining_time":0.2647364415},
{"learn":[1.370499482],"iteration":534,"passed_time":0.3038882275,"remaining_time":0.264127151},
{"learn":[1.36851469],"iteration":535,"passed_time":0.3044227226,"remaining_time":0.2635301181},
{"learn":[1.367600408],"iteration":536,"passed_time":0.3050270166,"remaining_time":0.2629934985},
{"learn":[1.361374564],"iteration":537,"passed_time":0.305622792,"remaining_time":0.2624493121},
{"learn":[1.360484009],"iteration":538,"passed_time":0.3062129582,"remaining_time":0.2619001368},
{"learn":[1.354926059],"iteration":539,"passed_time":0.3067785684,"remaining_time":0.2613298916},
{"learn":[1.348978426],"iteration":540,"passed_time":0.3072979759,"remaining_time":0.2607204638},
{"learn":[1.347954743],"iteration":541,"passed_time":0.3078127041,"remaining_time":0.2601074142},
{"learn":[1.347095029],"iteration":542,"passed_time":0.3083263325,"remaining_time":0.259493801},
{"learn":[1.346082227],"iteration":543,"passed_time":0.308839131,"remaining_time":0.2588798598},
{"learn":[1.342134617],"iteration":544,"passed_time":0.3093612481,"remaining_time":0.2582740695},
{"learn":[1.341265749],"iteration":545,"passed_time":0.3100413991,"remaining_time":0.2577999912},
{"learn":[1.339224346],"iteration":546,"passed_time":0.310614308,"remaining_time":0.2572363465},
{"learn":[1.33733233],"iteration":547,"passed_time":0.3111533334,"remaining_time":0.2566447202},
{"learn":[1.335644869],"iteration":548,"passed_time":0.3116777101,"remaining_time":0.2560412518},
{"learn":[1.331784641],"iteration":549,"passed_time":0.312194298,"remaining_time":0.2554316984},
{"learn":[1.330926481],"iteration":550,"passed_time":0.3127100961,"remaining_time":0.2548218387},
{"learn":[1.32904973],"iteration":551,"passed_time":0.3132319632,"remaining_time":0.2542172455},
{"learn":[1.328162228],"iteration":552,"passed_time":0.3137484711,"remaining_time":0.2536086195},
{"learn":[1.325369249],"iteration":553,"passed_time":0.3142571703,"remaining_time":0.2529940396},
{"learn":[1.32156173],"iteration":554,"passed_time":0.3147761179,"remaining_time":0.2523880585},
{"learn":[1.31965907],"iteration":555,"passed_time":0.3152898863,"remaining_time":0.2517782545},
{"learn":[1.317896525],"iteration":556,"passed_time":0.3158055243,"remaining_time":0.2511702824},
{"learn":[1.316801284],"iteration":557,"passed_time":0.3163229621,"remaining_time":0.2505640668},
{"learn":[1.315967661],"iteration":558,"passed_time":0.3168364006,"remaining_time":0.2499550137},
{"learn":[1.312250824],"iteration":559,"passed_time":0.3173526286,"remaining_time":0.2493484939},
{"learn":[1.310571229],"iteration":560,"passed_time":0.3178684366,"remaining_time":0.2487419673},
{"learn":[1.308880473],"iteration":561,"passed_time":0.3183859444,"remaining_time":0.2481370884},
{"learn":[1.305223184],"iteration":562,"passed_time":0.3189077815,"remaining_time":0.2475358802},
{"learn":[1.304281602],"iteration":563,"passed_time":0.3194214999,"remaining_time":0.2469286772},
{"learn":[1.300689509],"iteration":564,"passed_time":0.3199336486,"remaining_time":0.2463205967},
{"learn":[1.299807787],"iteration":565,"passed_time":0.3204510464,"remaining_time":0.2457168801},
{"learn":[1.296279376],"iteration":566,"passed_time":0.3209640249,"remaining_time":0.2451100931},
{"learn":[1.295690891],"iteration":567,"passed_time":0.3214758036,"remaining_time":0.2445027238},
{"learn":[1.294761684],"iteration":568,"passed_time":0.3219938213,"remaining_time":0.2439004165},
{"learn":[1.291295125],"iteration":569,"passed_time":0.3225158683,"remaining_time":0.2433014445},
{"learn":[1.291044475],"iteration":570,"passed_time":0.3230355458,"remaining_time":0.2427009617},
{"learn":[1.290918729],"iteration":571,"passed_time":0.3235371661,"remaining_time":0.2420872502},
{"learn":[1.290185102],"iteration":572,"passed_time":0.3240871775,"remaining_time":0.2415099909},
{"learn":[1.289337487],"iteration":573,"passed_time":0.3246830828,"remaining_time":0.2409668873},
{"learn":[1.286692555],"iteration":574,"passed_time":0.325242114,"remaining_time":0.2403963452},
{"learn":[1.281155787],"iteration":575,"passed_time":0.3257641011,"remaining_time":0.2397985744},
{"learn":[1.280620333],"iteration":576,"passed_time":0.3262759398,"remaining_time":0.2391936266},
{"learn":[1.28049725],"iteration":577,"passed_time":0.3267851789,"remaining_time":0.2385871029},
{"learn":[1.280378411],"iteration":578,"passed_time":0.3272987473,"remaining_time":0.2379840632},
{"learn":[1.278785053],"iteration":579,"passed_time":0.3278174649,"remaining_time":0.2373850608},
{"learn":[1.275403891],"iteration":580,"passed_time":0.3283281938,"remaining_time":0.2367805735},
{"learn":[1.272085928],"iteration":581,"passed_time":0.3288794062,"remaining_time":0.2362054842},
{"learn":[1.270157648],"iteration":582,"passed_time":0.3295998318,"remaining_time":0.2357515092},
{"learn":[1.268262836],"iteration":583,"passed_time":0.330316138,"remaining_time":0.2352936873},
{"learn":[1.267416706],"iteration":584,"passed_time":0.3309355796,"remaining_time":0.2347662658},
{"learn":[1.267297642],"iteration":585,"passed_time":0.3315132878,"remaining_time":0.2342090463},
{"learn":[1.266465181],"iteration":586,"passed_time":0.3321447775,"remaining_time":0.2336895964},
{"learn":[1.265799147],"iteration":587,"passed_time":0.3328283089,"remaining_time":0.23320623},
{"learn":[1.263237629],"iteration":588,"passed_time":0.3335036516,"remaining_time":0.23271647},
{"learn":[1.257891995],"iteration":589,"passed_time":0.3341421802,"remaining_time":0.2322004981},
{"learn":[1.256407471],"iteration":590,"passed_time":0.3347235878,"remaining_time":0.2316445811},
{"learn":[1.254552491],"iteration":591,"passed_time":0.335408269,"remaining_time":0.231159753},
{"learn":[1.253070046],"iteration":592,"passed_time":0.3360428782,"remaining_time":0.2306398844},
{"learn":[1.249816841],"iteration":593,"passed_time":0.3367151227,"remaining_time":0.2301453532},
{"learn":[1.248312737],"iteration":594,"passed_time":0.3374306278,"remaining_time":0.229679671},
{"learn":[1.245116255],"iteration":595,"passed_time":0.3381636913,"remaining_time":0.2292250525},
{"learn":[1.243308132],"iteration":596,"passed_time":0.3387344007,"remaining_time":0.2286599053},
{"learn":[1.238150778],"iteration":597,"passed_time":0.3392606571,"remaining_time":0.2280648564},
{"learn":[1.237229724],"iteration":598,"passed_time":0.3398732497,"remaining_time":0.227527835},
{"learn":[1.236409994],"iteration":599,"passed_time":0.3404815431,"remaining_time":0.2269876954},
{"learn":[1.234882709],"iteration":600,"passed_time":0.3410784583,"remaining_time":0.2264397751},
{"learn":[1.233349311],"iteration":601,"passed_time":0.3416836821,"remaining_time":0.2258971852},
{"learn":[1.230207095],"iteration":602,"passed_time":0.3423145819,"remaining_time":0.2253712919},
{"learn":[1.229366745],"iteration":603,"passed_time":0.342943712,"remaining_time":0.2248438906},
{"learn":[1.229229772],"iteration":604,"passed_time":0.3435446177,"remaining_time":0.2242977256},
{"learn":[1.226143682],"iteration":605,"passed_time":0.3440724739,"remaining_time":0.2237038856},
{"learn":[1.220578341],"iteration":606,"passed_time":0.3445937511,"remaining_time":0.2231060036},
{"learn":[1.21799056],"iteration":607,"passed_time":0.3451076394,"remaining_time":0.2225036096},
{"learn":[1.217157677],"iteration":608,"passed_time":0.3456197781,"remaining_time":0.221900383},
{"learn":[1.216349891],"iteration":609,"passed_time":0.3461338864,"remaining_time":0.2212987142},
{"learn":[1.216214133],"iteration":610,"passed_time":0.3466469549,"remaining_time":0.2206966701},
{"learn":[1.214709043],"iteration":611,"passed_time":0.3471671722,"remaining_time":0.2200994491},
{"learn":[1.21409033],"iteration":612,"passed_time":0.3476852999,"remaining_time":0.21950116},
{"learn":[1.21320023],"iteration":613,"passed_time":0.3482050074,"remaining_time":0.2189041252},
{"learn":[1.208315205],"iteration":614,"passed_time":0.3487289541,"remaining_time":0.2183099957},
{"learn":[1.206841048],"iteration":615,"passed_time":0.3492536108,"remaining_time":0.2177165366},
{"learn":[1.201571239],"iteration":616,"passed_time":0.3497771376,"remaining_time":0.2171225992},
{"learn":[1.200491837],"iteration":617,"passed_time":0.3502947454,"remaining_time":0.216525231},
{"learn":[1.19905878],"iteration":618,"passed_time":0.3508188121,"remaining_time":0.215932096},
{"learn":[1.197655522],"iteration":619,"passed_time":0.3513398694,"remaining_time":0.2153373393},
{"learn":[1.1925749],"iteration":620,"passed_time":0.3519859755,"remaining_time":0.214819138},
{"learn":[1.188290553],"iteration":621,"passed_time":0.3526020976,"remaining_time":0.2142823037},
{"learn":[1.185876386],"iteration":622,"passed_time":0.3532033421,"remaining_time":0.2137362118},
{"learn":[1.18108208],"iteration":623,"passed_time":0.3537670838,"remaining_time":0.2131673454},
{"learn":[1.1795151],"iteration":624,"passed_time":0.3543438809,"remaining_time":0.2126063286},
{"learn":[1.177997352],"iteration":625,"passed_time":0.3549565436,"remaining_time":0.212066689},
{"learn":[1.176465404],"iteration":626,"passed_time":0.3555618974,"remaining_time":0.2115224685},
{"learn":[1.174973975],"iteration":627,"passed_time":0.3561680112,"remaining_time":0.2109785034},
{"learn":[1.171569442],"iteration":628,"passed_time":0.3567750747,"remaining_time":0.210434901},
{"learn":[1.169059862],"iteration":629,"passed_time":0.3573678205,"remaining_time":0.2098826883},
{"learn":[1.167214762],"iteration":630,"passed_time":0.3579639968,"remaining_time":0.2093323531},
{"learn":[1.16590113],"iteration":631,"passed_time":0.3584909931,"remaining_time":0.2087415909},
{"learn":[1.164485673],"iteration":632,"passed_time":0.3590189692,"remaining_time":0.2081515983},
{"learn":[1.163096648],"iteration":633,"passed_time":0.3595340674,"remaining_time":0.207554367},
{"learn":[1.1600695],"iteration":634,"passed_time":0.3600553946,"remaining_time":0.2069609748},
{"learn":[1.157099185],"iteration":635,"passed_time":0.3605945289,"remaining_time":0.2063780008},
{"learn":[1.156897899],"iteration":636,"passed_time":0.3611823755,"remaining_time":0.2058229236},
{"learn":[1.155647542],"iteration":637,"passed_time":0.3617742415,"remaining_time":0.2052700242},
{"learn":[1.152729267],"iteration":638,"passed_time":0.3622914594,"remaining_time":0.2046748307},
{"learn":[1.152104523],"iteration":639,"passed_time":0.3628041479,"remaining_time":0.2040773332},
{"learn":[1.151514348],"iteration":640,"passed_time":0.3633150068,"remaining_time":0.2034790755},
{"learn":[1.15044215],"iteration":641,"passed_time":0.3638348642,"remaining_time":0.2028861081},
{"learn":[1.150322008],"iteration":642,"passed_time":0.3643528119,"remaining_time":0.2022923077},
{"learn":[1.149506682],"iteration":643,"passed_time":0.3648764587,"remaining_time":0.2017018933},
{"learn":[1.146634901],"iteration":644,"passed_time":0.3653920968,"remaining_time":0.2011072781},
{"learn":[1.144210768],"iteration":645,"passed_time":0.3659054752,"remaining_time":0.2005116691},
{"learn":[1.143514663],"iteration":646,"passed_time":0.3664219932,"remaining_time":0.1999180272},
{"learn":[1.140689266],"iteration":647,"passed_time":0.3669496581,"remaining_time":0.1993306785},
{"learn":[1.139866621],"iteration":648,"passed_time":0.3675465433,"remaining_time":0.1987809502},
{"learn":[1.138682495],"iteration":649,"passed_time":0.3681374694,"remaining_time":0.1982278682},
{"learn":[1.137807274],"iteration":650,"passed_time":0.3687305852,"remaining_time":0.1976758437},
{"learn":[1.136829526],"iteration":651,"passed_time":0.3693324696,"remaining_time":0.1971283733},
{"learn":[1.134047133],"iteration":652,"passed_time":0.3699575903,"remaining_time":0.196593084},
{"learn":[1.133933642],"iteration":653,"passed_time":0.3705751522,"remaining_time":0.1960535209},
{"learn":[1.133136822],"iteration":654,"passed_time":0.3711552013,"remaining_time":0.195493961},
{"learn":[1.132107116],"iteration":655,"passed_time":0.371679328,"remaining_time":0.1949050135},
{"learn":[1.129782118],"iteration":656,"passed_time":0.3721983755,"remaining_time":0.1943136116},
{"learn":[1.12704086],"iteration":657,"passed_time":0.3727204526,"remaining_time":0.1937240042},
{"learn":[1.125710192],"iteration":658,"passed_time":0.3732450393,"remaining_time":0.1931359004},
{"learn":[1.125148611],"iteration":659,"passed_time":0.3737625471,"remaining_time":0.1925443424},
{"learn":[1.124376663],"iteration":660,"passed_time":0.3742744357,"remaining_time":0.1919501267},
{"learn":[1.124240458],"iteration":661,"passed_time":0.3747864744,"remaining_time":0.1913562362},
{"learn":[1.121544183],"iteration":662,"passed_time":0.3753045121,"remaining_time":0.1907656419},
{"learn":[1.120918653],"iteration":663,"passed_time":0.3758139212,"remaining_time":0.1901708999},
{"learn":[1.120728596],"iteration":664,"passed_time":0.3763268597,"remaining_time":0.1895781925},
{"learn":[1.120544165],"iteration":665,"passed_time":0.3768387384,"remaining_time":0.1889851931},
{"learn":[1.120428369],"iteration":666,"passed_time":0.3773541065,"remaining_time":0.1883941791},
{"learn":[1.117779957],"iteration":667,"passed_time":0.3778664451,"remaining_time":0.1878018859},
{"learn":[1.117678276],"iteration":668,"passed_time":0.3783850527,"remaining_time":0.1872129334},
{"learn":[1.117115257],"iteration":669,"passed_time":0.37890607,"remaining_time":0.1866253777},
{"learn":[1.113178824],"iteration":670,"passed_time":0.3794252075,"remaining_time":0.1860370988},
{"learn":[1.112413169],"iteration":671,"passed_time":0.3799502041,"remaining_time":0.1854518853},
{"learn":[1.111630706],"iteration":672,"passed_time":0.3804662321,"remaining_time":0.1848624932},
{"learn":[1.110491381],"iteration":673,"passed_time":0.3809869194,"remaining_time":0.1842755723},
{"learn":[1.109738365],"iteration":674,"passed_time":0.3815009077,"remaining_time":0.1836856222},
{"learn":[1.109631602],"iteration":675,"passed_time":0.3820138263,"remaining_time":0.1830953842},
{"learn":[1.10872321],"iteration":676,"passed_time":0.3825233453,"remaining_time":0.1825037526},
{"learn":[1.104385408],"iteration":677,"passed_time":0.3830401832,"remaining_time":0.1819158392},
{"learn":[1.103642399],"iteration":678,"passed_time":0.3835601406,"remaining_time":0.1813296099},
{"learn":[1.101847674],"iteration":679,"passed_time":0.3840820277,"remaining_time":0.1807444836},
{"learn":[1.10031914],"iteration":680,"passed_time":0.3846051746,"remaining_time":0.1801601332},
{"learn":[1.100212336],"iteration":681,"passed_time":0.3851165434,"remaining_time":0.1795704704},
{"learn":[1.099590631],"iteration":682,"passed_time":0.3856296918,"remaining_time":0.1789818628},
{"learn":[1.099491291],"iteration":683,"passed_time":0.3861350416,"remaining_time":0.178389873},
{"learn":[1.098715107],"iteration":684,"passed_time":0.386654549,"remaining_time":0.1778046466},
{"learn":[1.096474501],"iteration":685,"passed_time":0.3871777159,"remaining_time":0.1772212869},
{"learn":[1.095518876],"iteration":686,"passed_time":0.3876978933,"remaining_time":0.1766367403},
{"learn":[1.093756611],"iteration":687,"passed_time":0.3882477959,"remaining_time":0.1760658609},
{"learn":[1.091158781],"iteration":688,"passed_time":0.3888513201,"remaining_time":0.1755192461},
{"learn":[1.087389789],"iteration":689,"passed_time":0.389443486,"remaining_time":0.1749673633},
{"learn":[1.086810956],"iteration":690,"passed_time":0.390035172,"remaining_time":0.1744151493},
{"learn":[1.085305282],"iteration":691,"passed_time":0.3906274879,"remaining_time":0.1738631016},
{"learn":[1.084532183],"iteration":692,"passed_time":0.3912177641,"remaining_time":0.173310034},
{"learn":[1.083625564],"iteration":693,"passed_time":0.3918094301,"remaining_time":0.1727574721},
{"learn":[1.0817166],"iteration":694,"passed_time":0.3924342797,"remaining_time":0.1722193601},
{"learn":[1.081593092],"iteration":695,"passed_time":0.3930022694,"remaining_time":0.1716561637},
{"learn":[1.081192668],"iteration":696,"passed_time":0.3935247564,"remaining_time":0.1710731724},
{"learn":[1.080621852],"iteration":697,"passed_time":0.394049673,"remaining_time":0.1704914058},
{"learn":[1.079873964],"iteration":698,"passed_time":0.394578609,"remaining_time":0.1699115326},
{"learn":[1.078146516],"iteration":699,"passed_time":0.3951316724,"remaining_time":0.1693421453},
{"learn":[1.075604535],"iteration":700,"passed_time":0.3956656775,"remaining_time":0.1687646756},
{"learn":[1.0749601],"iteration":701,"passed_time":0.3961937636,"remaining_time":0.168184817},
{"learn":[1.072463278],"iteration":702,"passed_time":0.396714151,"remaining_time":0.1676018533},
{"learn":[1.072350013],"iteration":703,"passed_time":0.3972276894,"remaining_time":0.1670161876},
{"learn":[1.072254429],"iteration":704,"passed_time":0.3977984575,"remaining_time":0.1664546737},
{"learn":[1.072150278],"iteration":705,"passed_time":0.3983289432,"remaining_time":0.1658763588},
{"learn":[1.071594995],"iteration":706,"passed_time":0.3989394462,"remaining_time":0.1653313405},
{"learn":[1.071449349],"iteration":707,"passed_time":0.3995352316,"remaining_time":0.1647800673},
{"learn":[1.071336503],"iteration":708,"passed_time":0.4001706719,"remaining_time":0.1642449443},
{"learn":[1.071247077],"iteration":709,"passed_time":0.4007508485,"remaining_time":0.1636869663},
{"learn":[1.067616655],"iteration":710,"passed_time":0.4013942963,"remaining_time":0.1631546436},
{"learn":[1.065922897],"iteration":711,"passed_time":0.4020390238,"remaining_time":0.1626225265},
{"learn":[1.063492896],"iteration":712,"passed_time":0.4026846025,"remaining_time":0.1620904361},
{"learn":[1.062191897],"iteration":713,"passed_time":0.4033073624,"remaining_time":0.1615488874},
{"learn":[1.062081506],"iteration":714,"passed_time":0.4039547895,"remaining_time":0.1610169441},
{"learn":[1.059693414],"iteration":715,"passed_time":0.4046053274,"remaining_time":0.160485912},
{"learn":[1.058881718],"iteration":716,"passed_time":0.4052647614,"remaining_time":0.1599580578},
{"learn":[1.058149556],"iteration":717,"passed_time":0.4058818434,"remaining_time":0.1594132031},
{"learn":[1.058040921],"iteration":718,"passed_time":0.4064648808,"remaining_time":0.1588548421},
{"learn":[1.057496119],"iteration":719,"passed_time":0.4070794334,"remaining_time":0.1583086685},
{"learn":[1.057123478],"iteration":720,"passed_time":0.4076097301,"remaining_time":0.1577297014},
{"learn":[1.057018883],"iteration":721,"passed_time":0.4081305074,"remaining_time":0.1571472037},
{"learn":[1.05355402],"iteration":722,"passed_time":0.4086635027,"remaining_time":0.1565695577},
{"learn":[1.052791908],"iteration":723,"passed_time":0.4091766412,"remaining_time":0.1559844654},
{"learn":[1.052003731],"iteration":724,"passed_time":0.4096934291,"remaining_time":0.1554009559},
{"learn":[1.049005529],"iteration":725,"passed_time":0.4102155861,"remaining_time":0.1548196565},
{"learn":[1.04823076],"iteration":726,"passed_time":0.4107365534,"remaining_time":0.154238073},
{"learn":[1.046147612],"iteration":727,"passed_time":0.4112532413,"remaining_time":0.1536550572},
{"learn":[1.042852621],"iteration":728,"passed_time":0.411784037,"remaining_time":0.1530774678},
{"learn":[1.041247363],"iteration":729,"passed_time":0.4123269507,"remaining_time":0.1525044886},
{"learn":[1.040028838],"iteration":730,"passed_time":0.4128497377,"remaining_time":0.1519241853},
{"learn":[1.039492682],"iteration":731,"passed_time":0.413363756,"remaining_time":0.1513408287},
{"learn":[1.037171439],"iteration":732,"passed_time":0.4138781943,"remaining_time":0.1507578143},
{"learn":[1.036813682],"iteration":733,"passed_time":0.4143904229,"remaining_time":0.150174186},
{"learn":[1.036710886],"iteration":734,"passed_time":0.4149030715,"remaining_time":0.1495909033},
{"learn":[1.035788754],"iteration":735,"passed_time":0.4154180797,"remaining_time":0.149008659},
{"learn":[1.035011977],"iteration":736,"passed_time":0.4159349776,"remaining_time":0.1484272715},
{"learn":[1.032729519],"iteration":737,"passed_time":0.4164515755,"remaining_time":0.1478459523},
{"learn":[1.032018224],"iteration":738,"passed_time":0.4169734726,"remaining_time":0.1472666798},
{"learn":[1.031264502],"iteration":739,"passed_time":0.4174897706,"remaining_time":0.1466855951},
{"learn":[1.031163079],"iteration":740,"passed_time":0.4180155158,"remaining_time":0.1461079873},
{"learn":[1.030445447],"iteration":741,"passed_time":0.4186157005,"remaining_time":0.1455564026},
{"learn":[1.029746457],"iteration":742,"passed_time":0.4192067466,"remaining_time":0.1450015261},
{"learn":[1.029224119],"iteration":743,"passed_time":0.4197978427,"remaining_time":0.1444465695},
{"learn":[1.028731923],"iteration":744,"passed_time":0.4203890988,"remaining_time":0.1438915707},
{"learn":[1.028645994],"iteration":745,"passed_time":0.4209749357,"remaining_time":0.1433346296},
{"learn":[1.02856466],"iteration":746,"passed_time":0.4215637222,"remaining_time":0.14277861},
{"learn":[1.028484989],"iteration":747,"passed_time":0.4221551482,"remaining_time":0.1422233922},
{"learn":[1.028007096],"iteration":748,"passed_time":0.4226885235,"remaining_time":0.141648624},
{"learn":[1.026506091],"iteration":749,"passed_time":0.4232100106,"remaining_time":0.1410700035},
{"learn":[1.025762156],"iteration":750,"passed_time":0.4237247389,"remaining_time":0.1404892942},
{"learn":[1.025272731],"iteration":751,"passed_time":0.4242447063,"remaining_time":0.1399104882},
{"learn":[1.024806251],"iteration":752,"passed_time":0.4247803612,"remaining_time":0.1393369843},
{"learn":[1.02472755],"iteration":753,"passed_time":0.4252983489,"remaining_time":0.1387578167},
{"learn":[1.024037821],"iteration":754,"passed_time":0.4258086578,"remaining_time":0.1381763194},
{"learn":[1.023960627],"iteration":755,"passed_time":0.426323736,"remaining_time":0.1375965497},
{"learn":[1.023283334],"iteration":756,"passed_time":0.4268464929,"remaining_time":0.1370194158},
{"learn":[1.021023806],"iteration":757,"passed_time":0.4273554321,"remaining_time":0.1364380139},
{"learn":[1.017821282],"iteration":758,"passed_time":0.4278635614,"remaining_time":0.1358565458},
{"learn":[1.017217663],"iteration":759,"passed_time":0.4283842986,"remaining_time":0.1352792522},
{"learn":[1.015185004],"iteration":760,"passed_time":0.4289032562,"remaining_time":0.1347015483},
{"learn":[1.013106776],"iteration":761,"passed_time":0.4294309724,"remaining_time":0.1341267342},
{"learn":[1.013018045],"iteration":762,"passed_time":0.429942881,"remaining_time":0.1335471334},
{"learn":[1.01294253],"iteration":763,"passed_time":0.4304473109,"remaining_time":0.1329653997},
{"learn":[1.012479793],"iteration":764,"passed_time":0.4309602594,"remaining_time":0.1323864849},
{"learn":[1.011282877],"iteration":765,"passed_time":0.4314833363,"remaining_time":0.1318108364},
{"learn":[1.011208707],"iteration":766,"passed_time":0.4319943751,"remaining_time":0.1312316681},
{"learn":[1.011110431],"iteration":767,"passed_time":0.4325120029,"remaining_time":0.1306546675},
{"learn":[1.009558261],"iteration":768,"passed_time":0.4330267411,"remaining_time":0.1300769535},
{"learn":[1.007345264],"iteration":769,"passed_time":0.4335497381,"remaining_time":0.1295018698},
{"learn":[1.005173871],"iteration":770,"passed_time":0.4340683957,"remaining_time":0.1289256324},
{"learn":[1.0051018],"iteration":771,"passed_time":0.4346695402,"remaining_time":0.1283739056},
{"learn":[1.004663491],"iteration":772,"passed_time":0.4352983815,"remaining_time":0.1278301845},
{"learn":[1.004592472],"iteration":773,"passed_time":0.4358232381,"remaining_time":0.1272558809},
{"learn":[1.003894133],"iteration":774,"passed_time":0.4363458951,"remaining_time":0.1266810663},
{"learn":[1.003812788],"iteration":775,"passed_time":0.4368615032,"remaining_time":0.1261043514},
{"learn":[1.00333699],"iteration":776,"passed_time":0.4374428496,"remaining_time":0.1255466608},
{"learn":[1.003244433],"iteration":777,"passed_time":0.4380525327,"remaining_time":0.1249969952},
{"learn":[1.002815327],"iteration":778,"passed_time":0.4386513876,"remaining_time":0.1244441035},
{"learn":[1.002747475],"iteration":779,"passed_time":0.4392460631,"remaining_time":0.1238899152},
{"learn":[1.000611687],"iteration":780,"passed_time":0.4398592369,"remaining_time":0.1233408104},
{"learn":[1.000522088],"iteration":781,"passed_time":0.4403893527,"remaining_time":0.1227683873},
{"learn":[1.000419583],"iteration":782,"passed_time":0.4409123597,"remaining_time":0.1221941022},
{"learn":[0.9973712937],"iteration":783,"passed_time":0.441438986,"remaining_time":0.1216209451},
{"learn":[0.9958276122],"iteration":784,"passed_time":0.4419585934,"remaining_time":0.1210459842},
{"learn":[0.9951442216],"iteration":785,"passed_time":0.4424809205,"remaining_time":0.1204719046},
{"learn":[0.9944043126],"iteration":786,"passed_time":0.443000198,"remaining_time":0.1198971311},
{"learn":[0.9936656261],"iteration":787,"passed_time":0.4435196655,"remaining_time":0.1193225496},
{"learn":[0.9932225988],"iteration":788,"passed_time":0.4440340737,"remaining_time":0.1187467548},
{"learn":[0.9917014585],"iteration":789,"passed_time":0.4445552709,"remaining_time":0.1181729201},
{"learn":[0.988721712],"iteration":790,"passed_time":0.4450748284,"remaining_time":0.1175987853},
{"learn":[0.9872237597],"iteration":791,"passed_time":0.4455868971,"remaining_time":0.1170228214},
{"learn":[0.9871588108],"iteration":792,"passed_time":0.4460977759,"remaining_time":0.1164467082},
{"learn":[0.9865055361],"iteration":793,"passed_time":0.4466777738,"remaining_time":0.1158886919},
{"learn":[0.985818836],"iteration":794,"passed_time":0.4472075796,"remaining_time":0.1153176778},
{"learn":[0.9843148185],"iteration":795,"passed_time":0.4477311564,"remaining_time":0.1147451707},
{"learn":[0.9835815158],"iteration":796,"passed_time":0.4482460546,"remaining_time":0.114170576},
{"learn":[0.9831472803],"iteration":797,"passed_time":0.4487580433,"remaining_time":0.1135953944},
{"learn":[0.9827578711],"iteration":798,"passed_time":0.4492814101,"remaining_time":0.1130232333},
{"learn":[0.9826936149],"iteration":799,"passed_time":0.4497910892,"remaining_time":0.1124477723},
{"learn":[0.9820496248],"iteration":800,"passed_time":0.4503114765,"remaining_time":0.1118751359},
{"learn":[0.9805684442],"iteration":801,"passed_time":0.4508323638,"remaining_time":0.1113027531},
{"learn":[0.9794256293],"iteration":802,"passed_time":0.4513444124,"remaining_time":0.1107283303},
{"learn":[0.9785397812],"iteration":803,"passed_time":0.4519107112,"remaining_time":0.1101672878},
{"learn":[0.9770797235],"iteration":804,"passed_time":0.4525194945,"remaining_time":0.1096165235},
{"learn":[0.9756194372],"iteration":805,"passed_time":0.4530893552,"remaining_time":0.1090562468},
{"learn":[0.9744949355],"iteration":806,"passed_time":0.4536157916,"remaining_time":0.1084855611},
{"learn":[0.9735944461],"iteration":807,"passed_time":0.4541343992,"remaining_time":0.1079131246},
{"learn":[0.9735309724],"iteration":808,"passed_time":0.4546416586,"remaining_time":0.1073381419},
{"learn":[0.9726395015],"iteration":809,"passed_time":0.4551571967,"remaining_time":0.1067652684},
{"learn":[0.9712116196],"iteration":810,"passed_time":0.4557591899,"remaining_time":0.1062126842},
{"learn":[0.9703388598],"iteration":811,"passed_time":0.4563655735,"remaining_time":0.1056609949},
{"learn":[0.9688959672],"iteration":812,"passed_time":0.4569602591,"remaining_time":0.1051064803},
{"learn":[0.9659965579],"iteration":813,"passed_time":0.4575193702,"remaining_time":0.1045437382},
{"learn":[0.964574165],"iteration":814,"passed_time":0.4580407574,"remaining_time":0.1039724419},
{"learn":[0.9631638312],"iteration":815,"passed_time":0.4585662439,"remaining_time":0.1034021923},
{"learn":[0.9631011557],"iteration":816,"passed_time":0.4590773927,"remaining_time":0.1028288407},
{"learn":[0.9611017198],"iteration":817,"passed_time":0.4595957304,"remaining_time":0.1022572407},
{"learn":[0.9610401564],"iteration":818,"passed_time":0.4601167876,"remaining_time":0.1016863719},
{"learn":[0.9608751727],"iteration":819,"passed_time":0.4606220873,"remaining_time":0.1011121655},
{"learn":[0.9602053519],"iteration":820,"passed_time":0.4611445443,"remaining_time":0.1005418678},
{"learn":[0.9595583641],"iteration":821,"passed_time":0.4616588626,"remaining_time":0.09996992403},
{"learn":[0.9594980725],"iteration":822,"passed_time":0.4622448747,"remaining_time":0.09941353927},
{"learn":[0.9590677433],"iteration":823,"passed_time":0.4628124694,"remaining_time":0.0988531488},
{"learn":[0.9583909333],"iteration":824,"passed_time":0.4634231924,"remaining_time":0.09830188929},
{"learn":[0.9569840245],"iteration":825,"passed_time":0.4640258866,"remaining_time":0.09774879452},
{"learn":[0.9556663032],"iteration":826,"passed_time":0.4646314604,"remaining_time":0.09719618217},
{"learn":[0.9537478308],"iteration":827,"passed_time":0.4652279357,"remaining_time":0.09664155185},
{"learn":[0.9512912049],"iteration":828,"passed_time":0.4658257207,"remaining_time":0.09608709076},
{"learn":[0.9508828857],"iteration":829,"passed_time":0.466409258,"remaining_time":0.09552960706},
{"learn":[0.9505873853],"iteration":830,"passed_time":0.4670001741,"remaining_time":0.09497356128},
{"learn":[0.949110313],"iteration":831,"passed_time":0.4675955095,"remaining_time":0.09441832404},
{"learn":[0.9490386384],"iteration":832,"passed_time":0.4681827063,"remaining_time":0.09386135888},
{"learn":[0.946663611],"iteration":833,"passed_time":0.4687900198,"remaining_time":0.09330832528},
{"learn":[0.9453654222],"iteration":834,"passed_time":0.4694161615,"remaining_time":0.09275888222},
{"learn":[0.9439383591],"iteration":835,"passed_time":0.470017586,"remaining_time":0.09220440682},
{"learn":[0.943781166],"iteration":836,"passed_time":0.4706646471,"remaining_time":0.09165870667},
{"learn":[0.9437108497],"iteration":837,"passed_time":0.4712675013,"remaining_time":0.09110421864},
{"learn":[0.9430382901],"iteration":838,"passed_time":0.4718658663,"remaining_time":0.09054875384},
{"learn":[0.9429696484],"iteration":839,"passed_time":0.4724563125,"remaining_time":0.08999167857},
{"learn":[0.9423707534],"iteration":840,"passed_time":0.4730702011,"remaining_time":0.08943895597},
{"learn":[0.9419930868],"iteration":841,"passed_time":0.4736009667,"remaining_time":0.0888704902},
{"learn":[0.9416102863],"iteration":842,"passed_time":0.4741225039,"remaining_time":0.08830039515},
{"learn":[0.940209037],"iteration":843,"passed_time":0.4746470406,"remaining_time":0.08773096958},
{"learn":[0.9396025383],"iteration":844,"passed_time":0.4751688577,"remaining_time":0.08716115141},
{"learn":[0.9392089864],"iteration":845,"passed_time":0.4756886851,"remaining_time":0.08659108452},
{"learn":[0.9391527743],"iteration":846,"passed_time":0.476198934,"remaining_time":0.08601940603},
{"learn":[0.9390107464],"iteration":847,"passed_time":0.476709013,"remaining_time":0.08544784195},
{"learn":[0.9379278715],"iteration":848,"passed_time":0.4772311201,"remaining_time":0.08487856199},
{"learn":[0.9368651826],"iteration":849,"passed_time":0.4777618757,"remaining_time":0.08431091925},
{"learn":[0.9358222988],"iteration":850,"passed_time":0.4782769239,"remaining_time":0.083740613},
{"learn":[0.9354386174],"iteration":851,"passed_time":0.4787902324,"remaining_time":0.08317013426},
{"learn":[0.9334430077],"iteration":852,"passed_time":0.4793066603,"remaining_time":0.08260032716},
{"learn":[0.9316199717],"iteration":853,"passed_time":0.4798260478,"remaining_time":0.08203115103},
{"learn":[0.9293089616],"iteration":854,"passed_time":0.4803402961,"remaining_time":0.08146121981},
{"learn":[0.928927277],"iteration":855,"passed_time":0.4808542445,"remaining_time":0.08089136823},
{"learn":[0.9276107866],"iteration":856,"passed_time":0.4813835804,"remaining_time":0.0803242147},
{"learn":[0.9272356981],"iteration":857,"passed_time":0.4818925995,"remaining_time":0.07975378687},
{"learn":[0.9262024378],"iteration":858,"passed_time":0.4824144766,"remaining_time":0.07918561258},
{"learn":[0.9241612614],"iteration":859,"passed_time":0.4829355439,"remaining_time":0.07861741412},
{"learn":[0.9221582075],"iteration":860,"passed_time":0.4834583108,"remaining_time":0.07804959954},
{"learn":[0.921486053],"iteration":861,"passed_time":0.483973549,"remaining_time":0.07748068417},
{"learn":[0.9201100577],"iteration":862,"passed_time":0.4844889171,"remaining_time":0.07691191384},
{"learn":[0.919523993],"iteration":863,"passed_time":0.4850134538,"remaining_time":0.07634471031},
{"learn":[0.9194483777],"iteration":864,"passed_time":0.4855265422,"remaining_time":0.07577581873},
{"learn":[0.9174898401],"iteration":865,"passed_time":0.4860438001,"remaining_time":0.07520770117},
{"learn":[0.9161170562],"iteration":866,"passed_time":0.4865619478,"remaining_time":0.07463983743},
{"learn":[0.9147846313],"iteration":867,"passed_time":0.4870736665,"remaining_time":0.07407111057},
{"learn":[0.9138660709],"iteration":868,"passed_time":0.4875853052,"remaining_time":0.07350250285},
{"learn":[0.9132970128],"iteration":869,"passed_time":0.4880990836,"remaining_time":0.07293434582},
{"learn":[0.9132424251],"iteration":870,"passed_time":0.4886316777,"remaining_time":0.07236910038},
{"learn":[0.9118891392],"iteration":871,"passed_time":0.4892302027,"remaining_time":0.07181360773},
{"learn":[0.9092173769],"iteration":872,"passed_time":0.4898206789,"remaining_time":0.07125684561},
{"learn":[0.9076073379],"iteration":873,"passed_time":0.4904103752,"remaining_time":0.07069989391},
{"learn":[0.9068537219],"iteration":874,"passed_time":0.490997122,"remaining_time":0.070142446},
{"learn":[0.9050887769],"iteration":875,"passed_time":0.4915860484,"remaining_time":0.06958523973},
{"learn":[0.9050289742],"iteration":876,"passed_time":0.4921655664,"remaining_time":0.06902664158},
{"learn":[0.9041450236],"iteration":877,"passed_time":0.4926915628,"remaining_time":0.06846055884},
{"learn":[0.9038102252],"iteration":878,"passed_time":0.4932074908,"remaining_time":0.06789318133},
{"learn":[0.9031953055],"iteration":879,"passed_time":0.4937192095,"remaining_time":0.06732534676},
{"learn":[0.9018522147],"iteration":880,"passed_time":0.4942392269,"remaining_time":0.06675876051},
{"learn":[0.9016587003],"iteration":881,"passed_time":0.4947504557,"remaining_time":0.06619110405},
{"learn":[0.9001008984],"iteration":882,"passed_time":0.4952722128,"remaining_time":0.06562497044},
{"learn":[0.8987788201],"iteration":883,"passed_time":0.495787371,"remaining_time":0.06505807131},
{"learn":[0.8961503291],"iteration":884,"passed_time":0.4963054987,"remaining_time":0.06449167497},
{"learn":[0.8954284407],"iteration":885,"passed_time":0.4968189971,"remaining_time":0.06392479195},
{"learn":[0.8951867562],"iteration":886,"passed_time":0.4973280362,"remaining_time":0.06335746121},
{"learn":[0.8936586934],"iteration":887,"passed_time":0.4978816383,"remaining_time":0.06279588231},
{"learn":[0.8927989826],"iteration":888,"passed_time":0.4984966906,"remaining_time":0.06224199399},
{"learn":[0.8914910128],"iteration":889,"passed_time":0.4990897876,"remaining_time":0.06168525465},
{"learn":[0.8911557808],"iteration":890,"passed_time":0.499615964,"remaining_time":0.061120247},
{"learn":[0.8898564293],"iteration":891,"passed_time":0.5003192423,"remaining_time":0.06057676924},
{"learn":[0.8888726891],"iteration":892,"passed_time":0.5009770166,"remaining_time":0.06002748127},
{"learn":[0.8862955858],"iteration":893,"passed_time":0.5016026174,"remaining_time":0.05947413585},
{"learn":[0.8862423569],"iteration":894,"passed_time":0.5021223149,"remaining_time":0.05890820454},
{"learn":[0.8847493584],"iteration":895,"passed_time":0.5027237491,"remaining_time":0.05835186373},
{"learn":[0.8840562194],"iteration":896,"passed_time":0.5033412822,"remaining_time":0.05779727098},
{"learn":[0.8827599604],"iteration":897,"passed_time":0.5038690684,"remaining_time":0.05723234407},
{"learn":[0.8824355237],"iteration":898,"passed_time":0.5043906555,"remaining_time":0.05666680334},
{"learn":[0.8809752295],"iteration":899,"passed_time":0.5049008644,"remaining_time":0.05610009605},
{"learn":[0.8800161591],"iteration":900,"passed_time":0.5054181123,"remaining_time":0.05553428759},
{"learn":[0.8793430612],"iteration":901,"passed_time":0.5059347502,"remaining_time":0.05496852053},
{"learn":[0.8784666849],"iteration":902,"passed_time":0.5064504583,"remaining_time":0.05440276241},
{"learn":[0.8771954578],"iteration":903,"passed_time":0.5069900913,"remaining_time":0.05383965572},
{"learn":[0.8769629949],"iteration":904,"passed_time":0.507596785,"remaining_time":0.05328364041},
{"learn":[0.8744295995],"iteration":905,"passed_time":0.5082059682,"remaining_time":0.05272777153},
{"learn":[0.8743654876],"iteration":906,"passed_time":0.5087956645,"remaining_time":0.05216978699},
{"learn":[0.873079485],"iteration":907,"passed_time":0.50939033,"remaining_time":0.05161223608},
{"learn":[0.8730169154],"iteration":908,"passed_time":0.5099744472,"remaining_time":0.05105354752},
{"learn":[0.8715892898],"iteration":909,"passed_time":0.5105627338,"remaining_time":0.05049521543},
{"learn":[0.8709329839],"iteration":910,"passed_time":0.51115335,"remaining_time":0.04993704517},
{"learn":[0.8705224185],"iteration":911,"passed_time":0.511738537,"remaining_time":0.04937827989},
{"learn":[0.8696151211],"iteration":912,"passed_time":0.5123311429,"remaining_time":0.04882016367},
{"learn":[0.8683466351],"iteration":913,"passed_time":0.5129256484,"remaining_time":0.04826215073},
{"learn":[0.8669487963],"iteration":914,"passed_time":0.5135107155,"remaining_time":0.04770318122},
{"learn":[0.866156855],"iteration":915,"passed_time":0.5141043812,"remaining_time":0.04714494325},
{"learn":[0.8643982723],"iteration":916,"passed_time":0.5147257927,"remaining_time":0.04658913936},
{"learn":[0.8635159559],"iteration":917,"passed_time":0.5152708559,"remaining_time":0.04602637274},
{"learn":[0.861025058],"iteration":918,"passed_time":0.5157999618,"remaining_time":0.0454622382},
{"learn":[0.8597677687],"iteration":919,"passed_time":0.5163190793,"remaining_time":0.04489731125},
{"learn":[0.8594388645],"iteration":920,"passed_time":0.5168414351,"remaining_time":0.04433276154},
{"learn":[0.8593683715],"iteration":921,"passed_time":0.5174122844,"remaining_time":0.04377240584},
{"learn":[0.8581004313],"iteration":922,"passed_time":0.5179322918,"remaining_time":0.04320778599},
{"learn":[0.856862535],"iteration":923,"passed_time":0.5184511794,"remaining_time":0.0426431706},
{"learn":[0.856812246],"iteration":924,"passed_time":0.5189678873,"remaining_time":0.04207847735},
{"learn":[0.8565103441],"iteration":925,"passed_time":0.5194782862,"remaining_time":0.04151338357},
{"learn":[0.8563610203],"iteration":926,"passed_time":0.5199810064,"remaining_time":0.04094780309},
{"learn":[0.854991552],"iteration":927,"passed_time":0.5205050331,"remaining_time":0.04038401119},
{"learn":[0.8543653026],"iteration":928,"passed_time":0.5210244006,"remaining_time":0.03981994881},
{"learn":[0.8543095545],"iteration":929,"passed_time":0.5215359994,"remaining_time":0.0392553978},
{"learn":[0.853446451],"iteration":930,"passed_time":0.5220445486,"remaining_time":0.03869073453},
{"learn":[0.8533918519],"iteration":931,"passed_time":0.5225600867,"remaining_time":0.0381267016},
{"learn":[0.8533442766],"iteration":932,"passed_time":0.5230657763,"remaining_time":0.0375620654},
{"learn":[0.8520913366],"iteration":933,"passed_time":0.5235888632,"remaining_time":0.03699878477},
{"learn":[0.8508830567],"iteration":934,"passed_time":0.5241118602,"remaining_time":0.03643558386},
{"learn":[0.8482842666],"iteration":935,"passed_time":0.5246340872,"remaining_time":0.03587241622},
{"learn":[0.8482373707],"iteration":936,"passed_time":0.5251485355,"remaining_time":0.03530881295},
{"learn":[0.846890399],"iteration":937,"passed_time":0.5256637836,"remaining_time":0.03474536736},
{"learn":[0.8455789166],"iteration":938,"passed_time":0.5261821713,"remaining_time":0.03418222838},
{"learn":[0.8454364668],"iteration":939,"passed_time":0.5267537805,"remaining_time":0.03362258173},
{"learn":[0.8447523189],"iteration":940,"passed_time":0.5273566547,"remaining_time":0.03306486995},
{"learn":[0.8437328281],"iteration":941,"passed_time":0.5279561394,"remaining_time":0.0325068536},
{"learn":[0.8425170147],"iteration":942,"passed_time":0.5285536745,"remaining_time":0.03194863144},
{"learn":[0.8411626789],"iteration":943,"passed_time":0.5291766556,"remaining_time":0.0313918355},
{"learn":[0.8411054502],"iteration":944,"passed_time":0.5299829275,"remaining_time":0.03084556721},
{"learn":[0.8400194638],"iteration":945,"passed_time":0.5306428129,"remaining_time":0.03029039312},
{"learn":[0.8398971824],"iteration":946,"passed_time":0.531196215,"remaining_time":0.02972903843},
{"learn":[0.8392935085],"iteration":947,"passed_time":0.531762575,"remaining_time":0.02916841129},
{"learn":[0.8391074968],"iteration":948,"passed_time":0.5323195465,"remaining_time":0.02860726752},
{"learn":[0.8387207011],"iteration":949,"passed_time":0.5329027648,"remaining_time":0.02804751394},
{"learn":[0.8363391993],"iteration":950,"passed_time":0.533474663,"remaining_time":0.02748712775},
{"learn":[0.8354947425],"iteration":951,"passed_time":0.5341723132,"remaining_time":0.02693305781},
{"learn":[0.8342405967],"iteration":952,"passed_time":0.5348224689,"remaining_time":0.02637634422},
{"learn":[0.832349014],"iteration":953,"passed_time":0.5353533246,"remaining_time":0.02581368232},
{"learn":[0.8321972277],"iteration":954,"passed_time":0.5359955626,"remaining_time":0.02525633541},
{"learn":[0.8308596144],"iteration":955,"passed_time":0.5366574062,"remaining_time":0.02469971326},
{"learn":[0.8300313168],"iteration":956,"passed_time":0.5372729984,"remaining_time":0.02414079303},
{"learn":[0.8289373642],"iteration":957,"passed_time":0.5378787522,"remaining_time":0.02358132316},
{"learn":[0.8281998022],"iteration":958,"passed_time":0.5385328483,"remaining_time":0.02302382354},
{"learn":[0.8279983417],"iteration":959,"passed_time":0.5392152499,"remaining_time":0.02246730208},
{"learn":[0.8262338758],"iteration":960,"passed_time":0.5399481434,"remaining_time":0.02191256774},
{"learn":[0.8250036653],"iteration":961,"passed_time":0.5406526527,"remaining_time":0.02135634179},
{"learn":[0.8237989341],"iteration":962,"passed_time":0.5413080274,"remaining_time":0.02079792006},
{"learn":[0.8227358933],"iteration":963,"passed_time":0.5419753214,"remaining_time":0.02023974229},
{"learn":[0.8214904544],"iteration":964,"passed_time":0.5426496143,"remaining_time":0.01968159223},
{"learn":[0.8204351472],"iteration":965,"passed_time":0.5432024764,"remaining_time":0.01911892774},
{"learn":[0.8202569594],"iteration":966,"passed_time":0.5437753245,"remaining_time":0.01855696557},
{"learn":[0.8197698044],"iteration":967,"passed_time":0.5443109094,"remaining_time":0.01799374907},
{"learn":[0.8196823232],"iteration":968,"passed_time":0.5448395954,"remaining_time":0.01743036889},
{"learn":[0.8186685509],"iteration":969,"passed_time":0.5453723808,"remaining_time":0.01686718703},
{"learn":[0.8168155616],"iteration":970,"passed_time":0.5461213415,"remaining_time":0.0163105241},
{"learn":[0.8151033335],"iteration":971,"passed_time":0.5467895054,"remaining_time":0.01575113802},
{"learn":[0.8141608398],"iteration":972,"passed_time":0.5475012223,"remaining_time":0.0151927369},
{"learn":[0.8130401238],"iteration":973,"passed_time":0.5480958079,"remaining_time":0.01463089426},
{"learn":[0.8129869759],"iteration":974,"passed_time":0.5487599624,"remaining_time":0.01407076827},
{"learn":[0.8120608016],"iteration":975,"passed_time":0.549417208,"remaining_time":0.01351025921},
{"learn":[0.8111518126],"iteration":976,"passed_time":0.5500427586,"remaining_time":0.01294880598},
{"learn":[0.8102596889],"iteration":977,"passed_time":0.5505975604,"remaining_time":0.01238563019},
{"learn":[0.8096800827],"iteration":978,"passed_time":0.5511234469,"remaining_time":0.01182185126},
{"learn":[0.8095126765],"iteration":979,"passed_time":0.5516367754,"remaining_time":0.01125789337},
{"learn":[0.8086362303],"iteration":980,"passed_time":0.5523148176,"remaining_time":0.01069722888},
{"learn":[0.8068436863],"iteration":981,"passed_time":0.5529676039,"remaining_time":0.01013586239},
{"learn":[0.8067607727],"iteration":982,"passed_time":0.5536216688,"remaining_time":0.009574332014},
{"learn":[0.8050853307],"iteration":983,"passed_time":0.5542681461,"remaining_time":0.009012490181},
{"learn":[0.8034478073],"iteration":984,"passed_time":0.5548573725,"remaining_time":0.008449604657},
{"learn":[0.8026446674],"iteration":985,"passed_time":0.5554175035,"remaining_time":0.007886252586},
{"learn":[0.8013144996],"iteration":986,"passed_time":0.5560118194,"remaining_time":0.007323357296},
{"learn":[0.8009166695],"iteration":987,"passed_time":0.5565782703,"remaining_time":0.006760059964},
{"learn":[0.800350113],"iteration":988,"passed_time":0.5571655471,"remaining_time":0.006196987884},
{"learn":[0.7990504687],"iteration":989,"passed_time":0.557789018,"remaining_time":0.005634232505},
{"learn":[0.7982704217],"iteration":990,"passed_time":0.5583964115,"remaining_time":0.005071208581},
{"learn":[0.7982080568],"iteration":991,"passed_time":0.5589728087,"remaining_time":0.004507845232},
{"learn":[0.7976586344],"iteration":992,"passed_time":0.5595870312,"remaining_time":0.003944722274},
{"learn":[0.7963882934],"iteration":993,"passed_time":0.5601847562,"remaining_time":0.003381396919},
{"learn":[0.7951426091],"iteration":994,"passed_time":0.5607816814,"remaining_time":0.002817998399},
{"learn":[0.7940766491],"iteration":995,"passed_time":0.5613776067,"remaining_time":0.002254528541},
{"learn":[0.7935422526],"iteration":996,"passed_time":0.5619705225,"remaining_time":0.001690984521},
{"learn":[0.7922986008],"iteration":997,"passed_time":0.5625170957,"remaining_time":0.001127288769},
{"learn":[0.7921382614],"iteration":998,"passed_time":0.5630429921,"remaining_time":0.0005636065987},
{"learn":[0.7909101975],"iteration":999,"passed_time":0.5635657891,"remaining_time":0}
]}